Workbook

Sheet Resumen
A1: Oportunidad digital – Miami-Dade y Broward
A2: Empresas establecidas sin web o con web obsoleta. Tablas dinámicas en hojas TD_*. Septiembre 2026.
A4: Indicadores | D4: Por condado | G4: Mercado
A5: Prospectos identificados | B5: =COUNTA(Prospectos!B5:B99) -> 95 | D5: Miami-Dade | E5: =COUNTIF(Prospectos!$E$5:$E$99,D5) -> 64 | G5: Establecimientos Miami-Dade (CBP 2023) | H5: 98394
A6: Sin sitio web | B6: =COUNTIF(Prospectos!$J$5:$J$99,"Sin sitio web") -> 15 | D6: Broward | E6: =COUNTIF(Prospectos!$E$5:$E$99,D6) -> 31 | G6: Establecimientos Broward (CBP 2022) | H6: 67274
A7: Sitio obsoleto / desordenado | B7: =COUNTIF(Prospectos!$J$5:$J$99,"Sitio obsoleto")+COUNTIF(Prospectos!$J$5:$J$99,"Presencia desordenada") -> 11 | G7: Solicitudes de negocio FL 2024 | H7: 634000
A8: Brecha confirmada (%) | B8: =IF(B5=0,0,(B6+B7)/B5) -> 0.27368421 | D8: Con brecha en Miami-Dade | E8: =COUNTIFS(Prospectos!$E$5:$E$99,"Miami-Dade",Prospectos!$J$5:$J$99,"Sin sitio web")+COUNTIFS(Prospectos!$E$5:$E$99,"Miami-Dade",Prospectos!$J$5:$J$99,"Sitio obsoleto")+COUNTIFS(Prospectos!$E$5:$E$99,"Miami-Dade",Prospectos!$J$5:$J$99,"Presencia desordenada") -> 14 | G8: Pymes EE.UU. sin web (Clutch 2025) | H8: 0.17
A9: Prioridad A | B9: =COUNTIF(Prospectos!$U$5:$U$99,"A") -> 13 | D9: Con brecha en Broward | E9: =COUNTIFS(Prospectos!$E$5:$E$99,"Broward",Prospectos!$J$5:$J$99,"Sin sitio web")+COUNTIFS(Prospectos!$E$5:$E$99,"Broward",Prospectos!$J$5:$J$99,"Sitio obsoleto")+COUNTIFS(Prospectos!$E$5:$E$99,"Broward",Prospectos!$J$5:$J$99,"Presencia desordenada") -> 12 | G9: Demandas ADA Title III FL 2025 | H9: 1823
A10: Pendientes de verificar web | B10: =COUNTIF(Prospectos!$J$5:$J$99,"No verificado") -> 50 | G10: CPC promedio Google Ads 2025 | H10: 5.26
A13: Hallazgos clave
A14: 1. Medley, Hialeah y Doral concentran la brecha más valiosa: manufactura, transporte y distribución B2B con 10–100 empleados, décadas operando y presencia solo en directorios (BBB, Manta, Yelp).
A15: 2. Transporte de carga (flotas de 55–66 camiones en Medley) y contratistas (Construct Group ~100 empleados con plantilla web sin editar) = prioridad A: ticket alto y competidores ya digitalizados.
A16: 3. En la náutica de Fort Lauderdale la mayoría ya tiene web. La oportunidad está en talleres antiguos (desde 1976–1999) con solo BBB/Yelp y en rediseño de sitios básicos.
A17: 4. HVAC, plomería y administración de propiedades (Davie, Sunrise, North Miami) muestran alta proporción de negocios sin dominio propio y CPL de Google Ads de $76–100: fácil demostrar ROI.
A18: 5. Florida es 2.º estado en demandas ADA (1,823 en 2025): una web accesible (WCAG 2.2 AA) es un argumento de venta con riesgo legal cuantificable.
A19: 6. Canal de contacto recomendado: email B2B 1 a 1 (CAN-SPAM) + visita presencial. Evitar llamadas/SMS automatizados (FTSA: $500–1,500 por violación).
A20: 7. Escalamiento: datasets abiertos BTR de Miami-Dade/Broward + SFTP de Sunbiz permiten pasar de ~95 a miles de prospectos con verificación automática de dominio.
A22: Hojas: Prospectos · TD_Area_Web · TD_Industria_Web · TD_Legal_Prioridad · TD_Redes · Oportunidad_Industria · Macro_Areas · Adopcion_Digital · Google_Ads · Legal_Cumplimiento · Parametros · Metodologia

Sheet Prospectos
A1: Prospectos: empresas con brecha digital
A2: Fuente por fila. Columnas azules/amarillas = completar tras verificación en Sunbiz y Google Maps.
A4: ID | B4: Empresa | C4: Municipio | D4: Barrio/zona | E4: Condado | F4: Sector (detalle) | G4: NAICS | H4: Industria (NAICS) | I4: Forma legal | J4: Estado web | K4: Redes sociales | L4: Tiene redes | M4: Evidencia | N4: Fuente | O4: Empleados (est.) | P4: Año fundación | Q4: Peso web | R4: Peso sector | S4: Señal tamaño | T4: Puntaje | U4: Prioridad | V4: Estado Sunbiz | W4: Próximo paso
A5: P001 | B5: Jonel Knitting Mills Inc | C5: Hialeah | E5: Miami-Dade | F5: Manufactura textil (tejidos de punto) | G5: 31 | H5: 31-33 Manufactura | I5: Inc | J5: Sin sitio web | K5: Ninguna encontrada | L5: No | M5: Manta: fundada 1987, ~25 empleados; sin web ni Facebook | N5: https://www.manta.com/c/mmn1h0x/jonel-knitting-mills-inc | O5: 25 | P5: 1987 | Q5: =IFERROR(VLOOKUP(J5,Parametros!$A$5:$B$9,2,FALSE()),0) -> 3 | R5: =IFERROR(VLOOKUP(H5,Parametros!$D$5:$E$16,2,FALSE()),1) -> 2 | S5: =IF(OR(N(O5)>=Parametros!$H$9,AND(N(P5)>0,N(P5)<=Parametros!$H$10)),1,0) -> 1 | T5: =Q5+R5+S5 -> 6 | U5: =IF(OR(V5="Inactive",V5="No encontrada"),"Descartada",IF(AND(T5>=Parametros!$H$5,S5=1),"A",IF(T5>=Parametros!$H$6,"B","C"))) -> A | V5: Pendiente
A6: P002 | B6: Steel Works Rebar Fabricators LLC | C6: Medley | E6: Miami-Dade | F6: Fabricación de acero/varilla | G6: 33 | H6: 31-33 Manufactura | I6: LLC | J6: Sin sitio web | K6: Facebook | L6: Sí | M6: Est. 2007, 10-19 empleados; solo directorios y Facebook | N6: https://www.manta.com/c/mmcwr0p/steel-works-rebar-fabricators-llc | O6: 10 | P6: 2007 | Q6: =IFERROR(VLOOKUP(J6,Parametros!$A$5:$B$9,2,FALSE()),0) -> 3 | R6: =IFERROR(VLOOKUP(H6,Parametros!$D$5:$E$16,2,FALSE()),1) -> 2 | S6: =IF(OR(N(O6)>=Parametros!$H$9,AND(N(P6)>0,N(P6)<=Parametros!$H$10)),1,0) -> 1 | T6: =Q6+R6+S6 -> 6 | U6: =IF(OR(V6="Inactive",V6="No encontrada"),"Descartada",IF(AND(T6>=Parametros!$H$5,S6=1),"A",IF(T6>=Parametros!$H$6,"B","C"))) -> A | V6: Pendiente
A7: P003 | B7: All Welding and Machine Shop Inc | C7: Medley | E7: Miami-Dade | F7: Soldadura/taller industrial | G7: 33 | H7: 31-33 Manufactura | I7: Inc | J7: Sin sitio web | K7: Ninguna encontrada | L7: No | M7: Solo YellowPages, Superpages, Manta, Waze | N7: https://www.yellowpages.com/medley-fl/mip/all-welding-and-machine-shop-inc-474064250 | Q7: =IFERROR(VLOOKUP(J7,Parametros!$A$5:$B$9,2,FALSE()),0) -> 3 | R7: =IFERROR(VLOOKUP(H7,Parametros!$D$5:$E$16,2,FALSE()),1) -> 2 | S7: =IF(OR(N(O7)>=Parametros!$H$9,AND(N(P7)>0,N(P7)<=Parametros!$H$10)),1,0) -> 0 | T7: =Q7+R7+S7 -> 5 | U7: =IF(OR(V7="Inactive",V7="No encontrada"),"Descartada",IF(AND(T7>=Parametros!$H$5,S7=1),"A",IF(T7>=Parametros!$H$6,"B","C"))) -> B | V7: Pendiente
A8: P004 | B8: Hialeah Plumbing Supply Company | C8: Hialeah | E8: Miami-Dade | F8: Distribución suministros de plomería | G8: 42 | H8: 42 Comercio mayorista | I8: Corp | J8: Sin sitio web | K8: Ninguna encontrada | L8: No | M8: Sunbiz: registrada 05/17/1989, Active | Forma legal fuente: Corp (Sunbiz: Florida Profit Corp) | N8: https://search.sunbiz.org/Inquiry/CorporationSearch/ByName | P8: 1989 | Q8: =IFERROR(VLOOKUP(J8,Parametros!$A$5:$B$9,2,FALSE()),0) -> 3 | R8: =IFERROR(VLOOKUP(H8,Parametros!$D$5:$E$16,2,FALSE()),1) -> 2 | S8: =IF(OR(N(O8)>=Parametros!$H$9,AND(N(P8)>0,N(P8)<=Parametros!$H$10)),1,0) -> 1 | T8: =Q8+R8+S8 -> 6 | U8: =IF(OR(V8="Inactive",V8="No encontrada"),"Descartada",IF(AND(T8>=Parametros!$H$5,S8=1),"A",IF(T8>=Parametros!$H$6,"B","C"))) -> A | V8: Active
A9: P005 | B9: Florida Paving & Trucking Inc | C9: Homestead | E9: Miami-Dade | F9: Pavimentación/movimiento de tierra | G9: 23 | H9: 23 Construcción y oficios | I9: Inc | J9: Sin sitio web | K9: Nextdoor | L9: Sí | M9: Est. 1992; solo BBB, D&B, Manta, Yelp, Procore | N9: https://www.bbb.org/us/fl/homestead/profile/paving-contractors/florida-paving-trucking-inc-0633-5003759 | P9: 1992 | Q9: =IFERROR(VLOOKUP(J9,Parametros!$A$5:$B$9,2,FALSE()),0) -> 3 | R9: =IFERROR(VLOOKUP(H9,Parametros!$D$5:$E$16,2,FALSE()),1) -> 3 | S9: =IF(OR(N(O9)>=Parametros!$H$9,AND(N(P9)>0,N(P9)<=Parametros!$H$10)),1,0) -> 1 | T9: =Q9+R9+S9 -> 7 | U9: =IF(OR(V9="Inactive",V9="No encontrada"),"Descartada",IF(AND(T9>=Parametros!$H$5,S9=1),"A",IF(T9>=Parametros!$H$6,"B","C"))) -> A | V9: Pendiente
A10: P006 | B10: Marante Forwarding Co Inc | C10: Hialeah | E10: Miami-Dade | F10: Logística - freight forwarding | G10: 48 | H10: 48-49 Transporte y logística | I10: Inc | J10: Sin sitio web | K10: Ninguna encontrada | L10: No | M10: Est. 1970; licencia OTI revocada 2003: verificar Sunbiz | Forma legal fuente: Inc (posible inactiva) | N10: https://www.manta.com/c/mm2vydb/marante-forwarding-co-inc | P10: 1970 | Q10: =IFERROR(VLOOKUP(J10,Parametros!$A$5:$B$9,2,FALSE()),0) -> 3 | R10: =IFERROR(VLOOKUP(H10,Parametros!$D$5:$E$16,2,FALSE()),1) -> 3 | S10: =IF(OR(N(O10)>=Parametros!$H$9,AND(N(P10)>0,N(P10)<=Parametros!$H$10)),1,0) -> 1 | T10: =Q10+R10+S10 -> 7 | U10: =IF(OR(V10="Inactive",V10="No encontrada"),"Descartada",IF(AND(T10>=Parametros!$H$5,S10=1),"A",IF(T10>=Parametros!$H$6,"B","C"))) -> A | V10: Pendiente | W10: Verificar Sunbiz (posible inactiva)
A11: P007 | B11: Truck Brokerage by National Inc | C11: Medley | E11: Miami-Dade | F11: Transporte de carga (roca/arena) | G11: 48 | H11: 48-49 Transporte y logística | I11: Inc | J11: Sitio obsoleto | K11: Ninguna encontrada | L11: No | M11: Est. 1986, 55 camiones (FMCSA); web http sin HTTPS, páginas .html estáticas | N11: http://www.truckbrokeragebynational.com/ | O11: 55 | P11: 1986 | Q11: =IFERROR(VLOOKUP(J11,Parametros!$A$5:$B$9,2,FALSE()),0) -> 3 | R11: =IFERROR(VLOOKUP(H11,Parametros!$D$5:$E$16,2,FALSE()),1) -> 3 | S11: =IF(OR(N(O11)>=Parametros!$H$9,AND(N(P11)>0,N(P11)<=Parametros!$H$10)),1,0) -> 1 | T11: =Q11+R11+S11 -> 7 | U11: =IF(OR(V11="Inactive",V11="No encontrada"),"Descartada",IF(AND(T11>=Parametros!$H$5,S11=1),"A",IF(T11>=Parametros!$H$6,"B","C"))) -> A | V11: Pendiente
A12: P008 | B12: Construct Group Corp | C12: Hialeah Gardens | E12: Miami-Dade | F12: Contratista civil (FDOT) | G12: 23 | H12: 23 Construcción y oficios | I12: Corp | J12: Sitio obsoleto | K12: Yelp | L12: Sí | M12: Est. 2001, ~100 empleados, 625 proyectos; título web 'HOME | My Site' (plantilla sin personalizar) | N12: https://www.constructgroupcorp.com/ | O12: 100 | P12: 2001 | Q12: =IFERROR(VLOOKUP(J12,Parametros!$A$5:$B$9,2,FALSE()),0) -> 3 | R12: =IFERROR(VLOOKUP(H12,Parametros!$D$5:$E$16,2,FALSE()),1) -> 3 | S12: =IF(OR(N(O12)>=Parametros!$H$9,AND(N(P12)>0,N(P12)<=Parametros!$H$10)),1,0) -> 1 | T12: =Q12+R12+S12 -> 7 | U12: =IF(OR(V12="Inactive",V12="No encontrada"),"Descartada",IF(AND(T12>=Parametros!$H$5,S12=1),"A",IF(T12>=Parametros!$H$6,"B","C"))) -> A | V12: Pendiente
A13: P009 | B13: Professional Plumbing Corp | C13: Hialeah | E13: Miami-Dade | F13: Contratista de plomería comercial | G13: 23 | H13: 23 Construcción y oficios | I13: Corp | J13: Sitio obsoleto | K13: Facebook | L13: Sí | M13: Desde 1973 (W Hotel, Fontainebleau); dos dominios, uno en http | N13: https://www.buildzoom.com/contractor/professional-plumbing-corp | P13: 1973 | Q13: =IFERROR(VLOOKUP(J13,Parametros!$A$5:$B$9,2,FALSE()),0) -> 3 | R13: =IFERROR(VLOOKUP(H13,Parametros!$D$5:$E$16,2,FALSE()),1) -> 3 | S13: =IF(OR(N(O13)>=Parametros!$H$9,AND(N(P13)>0,N(P13)<=Parametros!$H$10)),1,0) -> 1 | T13: =Q13+R13+S13 -> 7 | U13: =IF(OR(V13="Inactive",V13="No encontrada"),"Descartada",IF(AND(T13>=Parametros!$H$5,S13=1),"A",IF(T13>=Parametros!$H$6,"B","C"))) -> A | V13: Pendiente
A14: P010 | B14: AA Florida Pallets Inc | C14: Medley | E14: Miami-Dade | F14: Fabricación/reciclaje de paletas | G14: 32 | H14: 31-33 Manufactura | I14: Inc | J14: Sitio obsoleto | K14: Ninguna encontrada | L14: No | M14: Título web con errata 'Welcom to AA Florida Pallets' | N14: https://www.manta.com/c/mhx9tn8/aa-florida-pallets-inc | Q14: =IFERROR(VLOOKUP(J14,Parametros!$A$5:$B$9,2,FALSE()),0) -> 3 | R14: =IFERROR(VLOOKUP(H14,Parametros!$D$5:$E$16,2,FALSE()),1) -> 2 | S14: =IF(OR(N(O14)>=Parametros!$H$9,AND(N(P14)>0,N(P14)<=Parametros!$H$10)),1,0) -> 0 | T14: =Q14+R14+S14 -> 5 | U14: =IF(OR(V14="Inactive",V14="No encontrada"),"Descartada",IF(AND(T14>=Parametros!$H$5,S14=1),"A",IF(T14>=Parametros!$H$6,"B","C"))) -> B | V14: Pendiente
A15: P011 | B15: High Quality Trucking Inc | C15: Medley | E15: Miami-Dade | F15: Transporte de carga/contenedores | G15: 48 | H15: 48-49 Transporte y logística | I15: Inc | J15: Sitio obsoleto | K15: Ninguna encontrada | L15: No | M15: Est. 2006, 66 camiones; dominio no coincide con la marca | N15: https://www.carriersource.io/carriers/high-quality-trucking-inc | O15: 66 | P15: 2006 | Q15: =IFERROR(VLOOKUP(J15,Parametros!$A$5:$B$9,2,FALSE()),0) -> 3 | R15: =IFERROR(VLOOKUP(H15,Parametros!$D$5:$E$16,2,FALSE()),1) -> 3 | S15: =IF(OR(N(O15)>=Parametros!$H$9,AND(N(P15)>0,N(P15)<=Parametros!$H$10)),1,0) -> 1 | T15: =Q15+R15+S15 -> 7 | U15: =IF(OR(V15="Inactive",V15="No encontrada"),"Descartada",IF(AND(T15>=Parametros!$H$5,S15=1),"A",IF(T15>=Parametros!$H$6,"B","C"))) -> A | V15: Pendiente
A16: P012 | B16: Hialeah Bakery and Foods Inc | C16: Hialeah | E16: Miami-Dade | F16: Panadería | G16: 31 | H16: 31-33 Manufactura | I16: Inc | J16: Tiene web (auditar) | K16: Facebook | L16: Sí | M16: Est. 1996, 24h; contacto con Gmail (señal de baja madurez digital) | N16: https://www.facebook.com/hialeahbakery/ | P16: 1996 | Q16: =IFERROR(VLOOKUP(J16,Parametros!$A$5:$B$9,2,FALSE()),0) -> 1 | R16: =IFERROR(VLOOKUP(H16,Parametros!$D$5:$E$16,2,FALSE()),1) -> 2 | S16: =IF(OR(N(O16)>=Parametros!$H$9,AND(N(P16)>0,N(P16)<=Parametros!$H$10)),1,0) -> 1 | T16: =Q16+R16+S16 -> 4 | U16: =IF(OR(V16="Inactive",V16="No encontrada"),"Descartada",IF(AND(T16>=Parametros!$H$5,S16=1),"A",IF(T16>=Parametros!$H$6,"B","C"))) -> B | V16: Pendiente
A17: P013 | B17: Los Tres Conejitos Bakery | C17: Hialeah | E17: Miami-Dade | F17: Panadería | G17: 31 | H17: 31-33 Manufactura | I17: No verificado | J17: No verificado | K17: Yelp | L17: Sí | M17: Est. 2001, familiar; solo Yelp | N17: https://www.yelp.com/biz/los-tres-conejitos-bakery-hialeah | P17: 2001 | Q17: =IFERROR(VLOOKUP(J17,Parametros!$A$5:$B$9,2,FALSE()),0) -> 1 | R17: =IFERROR(VLOOKUP(H17,Parametros!$D$5:$E$16,2,FALSE()),1) -> 2 | S17: =IF(OR(N(O17)>=Parametros!$H$9,AND(N(P17)>0,N(P17)<=Parametros!$H$10)),1,0) -> 0 | T17: =Q17+R17+S17 -> 3 | U17: =IF(OR(V17="Inactive",V17="No encontrada"),"Descartada",IF(AND(T17>=Parametros!$H$5,S17=1),"A",IF(T17>=Parametros!$H$6,"B","C"))) -> C | V17: Pendiente
A18: P014 | B18: Tango Body Shop | C18: Hialeah | E18: Miami-Dade | F18: Automotriz - carrocería | G18: 81 | H18: 81 Servicios (auto, náutico, reparación) | I18: No verificado | J18: No verificado | K18: Yelp | L18: Sí | M18: 20+ años; solo Yelp | N18: https://www.yelp.com/biz/tango-body-shop-hialeah | Q18: =IFERROR(VLOOKUP(J18,Parametros!$A$5:$B$9,2,FALSE()),0) -> 1 | R18: =IFERROR(VLOOKUP(H18,Parametros!$D$5:$E$16,2,FALSE()),1) -> 2 | S18: =IF(OR(N(O18)>=Parametros!$H$9,AND(N(P18)>0,N(P18)<=Parametros!$H$10)),1,0) -> 0 | T18: =Q18+R18+S18 -> 3 | U18: =IF(OR(V18="Inactive",V18="No encontrada"),"Descartada",IF(AND(T18>=Parametros!$H$5,S18=1),"A",IF(T18>=Parametros!$H$6,"B","C"))) -> C | V18: Pendiente
A19: P015 | B19: Pro Collision Center LLC | C19: Hialeah | E19: Miami-Dade | F19: Automotriz - carrocería | G19: 81 | H19: 81 Servicios (auto, náutico, reparación) | I19: LLC | J19: Presencia desordenada | K19: Yelp; BBB | L19: Sí | M19: Desde 2008, I-Car Gold; dos dominios distintos | N19: https://www.bbb.org/us/fl/hialeah/profile/auto-body-repair-and-painting/procollision-center-llc-0633-90024812 | P19: 2008 | Q19: =IFERROR(VLOOKUP(J19,Parametros!$A$5:$B$9,2,FALSE()),0) -> 2 | R19: =IFERROR(VLOOKUP(H19,Parametros!$D$5:$E$16,2,FALSE()),1) -> 2 | S19: =IF(OR(N(O19)>=Parametros!$H$9,AND(N(P19)>0,N(P19)<=Parametros!$H$10)),1,0) -> 0 | T19: =Q19+R19+S19 -> 4 | U19: =IF(OR(V19="Inactive",V19="No encontrada"),"Descartada",IF(AND(T19>=Parametros!$H$5,S19=1),"A",IF(T19>=Parametros!$H$6,"B","C"))) -> B | V19: Pendiente
A20: P016 | B20: Sari Express Forwarders Inc | C20: Hialeah | E20: Miami-Dade | F20: Logística - freight forwarding | G20: 48 | H20: 48-49 Transporte y logística | I20: Inc | J20: No verificado | K20: Ninguna encontrada | L20: No | M20: Solo Manta | N20: https://www.manta.com/c/mm43fmb/sari-express-forwarders-inc | Q20: =IFERROR(VLOOKUP(J20,Parametros!$A$5:$B$9,2,FALSE()),0) -> 1 | R20: =IFERROR(VLOOKUP(H20,Parametros!$D$5:$E$16,2,FALSE()),1) -> 3 | S20: =IF(OR(N(O20)>=Parametros!$H$9,AND(N(P20)>0,N(P20)<=Parametros!$H$10)),1,0) -> 0 | T20: =Q20+R20+S20 -> 4 | U20: =IF(OR(V20="Inactive",V20="No encontrada"),"Descartada",IF(AND(T20>=Parametros!$H$5,S20=1),"A",IF(T20>=Parametros!$H$6,"B","C"))) -> B | V20: Pendiente
A21: P017 | B21: Global Cargo Connection Inc | C21: Hialeah | E21: Miami-Dade | F21: Logística - consolidación de carga | G21: 48 | H21: 48-49 Transporte y logística | I21: Inc | J21: No verificado | K21: Ninguna encontrada | L21: No | M21: Categoría Freight Forwarding Manta Hialeah | N21: https://www.manta.com/mb_55_B52DB05K_33S/freight_forwarding/hialeah_fl | Q21: =IFERROR(VLOOKUP(J21,Parametros!$A$5:$B$9,2,FALSE()),0) -> 1 | R21: =IFERROR(VLOOKUP(H21,Parametros!$D$5:$E$16,2,FALSE()),1) -> 3 | S21: =IF(OR(N(O21)>=Parametros!$H$9,AND(N(P21)>0,N(P21)<=Parametros!$H$10)),1,0) -> 0 | T21: =Q21+R21+S21 -> 4 | U21: =IF(OR(V21="Inactive",V21="No encontrada"),"Descartada",IF(AND(T21>=Parametros!$H$5,S21=1),"A",IF(T21>=Parametros!$H$6,"B","C"))) -> B | V21: Pendiente
A22: P018 | B22: Marante Distributors Corp | C22: Hialeah | E22: Miami-Dade | F22: Distribución mayorista | G22: 42 | H22: 42 Comercio mayorista | I22: Corp | J22: No verificado | K22: Ninguna encontrada | L22: No | M22: Solo Yahoo Local | N22: https://local.yahoo.com/info-211983306-marante-distributors-corp-hialeah/ | Q22: =IFERROR(VLOOKUP(J22,Parametros!$A$5:$B$9,2,FALSE()),0) -> 1 | R22: =IFERROR(VLOOKUP(H22,Parametros!$D$5:$E$16,2,FALSE()),1) -> 2 | S22: =IF(OR(N(O22)>=Parametros!$H$9,AND(N(P22)>0,N(P22)<=Parametros!$H$10)),1,0) -> 0 | T22: =Q22+R22+S22 -> 3 | U22: =IF(OR(V22="Inactive",V22="No encontrada"),"Descartada",IF(AND(T22>=Parametros!$H$5,S22=1),"A",IF(T22>=Parametros!$H$6,"B","C"))) -> C | V22: Pendiente
A23: P019 | B23: Medina & Son Plumbing Supply Inc | C23: Hialeah | E23: Miami-Dade | F23: Distribución suministros de plomería | G23: 42 | H23: 42 Comercio mayorista | I23: Inc | J23: Tiene web (auditar) | K23: Facebook; Yelp | L23: Sí | M23: Desde 1987, 84+ reseñas | N23: https://www.yelp.com/biz/medina-and-son-plumbing-supply-hialeah | P23: 1987 | Q23: =IFERROR(VLOOKUP(J23,Parametros!$A$5:$B$9,2,FALSE()),0) -> 1 | R23: =IFERROR(VLOOKUP(H23,Parametros!$D$5:$E$16,2,FALSE()),1) -> 2 | S23: =IF(OR(N(O23)>=Parametros!$H$9,AND(N(P23)>0,N(P23)<=Parametros!$H$10)),1,0) -> 1 | T23: =Q23+R23+S23 -> 4 | U23: =IF(OR(V23="Inactive",V23="No encontrada"),"Descartada",IF(AND(T23>=Parametros!$H$5,S23=1),"A",IF(T23>=Parametros!$H$6,"B","C"))) -> B | V23: Pendiente
A24: P020 | B24: Manny's Plumbing Service | C24: Hialeah | E24: Miami-Dade | F24: Plomería | G24: 23 | H24: 23 Construcción y oficios | I24: No verificado | J24: No verificado | K24: Ninguna encontrada | L24: No | M24: Manta: est. 1993 | N24: https://www.manta.com/c/mmf1sbc/manny-s-plumbing-service | Q24: =IFERROR(VLOOKUP(J24,Parametros!$A$5:$B$9,2,FALSE()),0) -> 1 | R24: =IFERROR(VLOOKUP(H24,Parametros!$D$5:$E$16,2,FALSE()),1) -> 3 | S24: =IF(OR(N(O24)>=Parametros!$H$9,AND(N(P24)>0,N(P24)<=Parametros!$H$10)),1,0) -> 0 | T24: =Q24+R24+S24 -> 4 | U24: =IF(OR(V24="Inactive",V24="No encontrada"),"Descartada",IF(AND(T24>=Parametros!$H$5,S24=1),"A",IF(T24>=Parametros!$H$6,"B","C"))) -> B | V24: Pendiente
A25: P021 | B25: All Star Aluminum Windows & Doors Inc | C25: Hialeah | E25: Miami-Dade | F25: Ventanas/puertas de aluminio | G25: 33 | H25: 31-33 Manufactura | I25: Inc | J25: Tiene web (auditar) | K25: Facebook; Yelp; Nextdoor | L25: Sí | M25: Fundada 2003 | N25: https://www.bbb.org/us/fl/hialeah/profile/impact-windows/all-star-aluminum-windows-doors-inc-0633-90034252 | P25: 2003 | Q25: =IFERROR(VLOOKUP(J25,Parametros!$A$5:$B$9,2,FALSE()),0) -> 1 | R25: =IFERROR(VLOOKUP(H25,Parametros!$D$5:$E$16,2,FALSE()),1) -> 2 | S25: =IF(OR(N(O25)>=Parametros!$H$9,AND(N(P25)>0,N(P25)<=Parametros!$H$10)),1,0) -> 0 | T25: =Q25+R25+S25 -> 3 | U25: =IF(OR(V25="Inactive",V25="No encontrada"),"Descartada",IF(AND(T25>=Parametros!$H$5,S25=1),"A",IF(T25>=Parametros!$H$6,"B","C"))) -> C | V25: Pendiente
A26: P022 | B26: Panther & Co Inc | C26: Medley | E26: Miami-Dade | F26: Transporte y almacenaje | G26: 48 | H26: 48-49 Transporte y logística | I26: Inc | J26: Tiene web (auditar) | K26: Facebook; Instagram | L26: Sí | M26: Est. 1989, ~17 empleados, ~$2.7M | N26: https://www.manta.com/c/mtqlxt4/panther-co-inc | O26: 17 | P26: 1989 | Q26: =IFERROR(VLOOKUP(J26,Parametros!$A$5:$B$9,2,FALSE()),0) -> 1 | R26: =IFERROR(VLOOKUP(H26,Parametros!$D$5:$E$16,2,FALSE()),1) -> 3 | S26: =IF(OR(N(O26)>=Parametros!$H$9,AND(N(P26)>0,N(P26)<=Parametros!$H$10)),1,0) -> 1 | T26: =Q26+R26+S26 -> 5 | U26: =IF(OR(V26="Inactive",V26="No encontrada"),"Descartada",IF(AND(T26>=Parametros!$H$5,S26=1),"A",IF(T26>=Parametros!$H$6,"B","C"))) -> B | V26: Pendiente
A27: P023 | B27: Medley Steel and Supply Inc | C27: Medley | E27: Miami-Dade | F27: Distribución de acero | G27: 42 | H27: 42 Comercio mayorista | I27: Inc | J27: Tiene web (auditar) | K27: LinkedIn | L27: Sí | M27: Desde 1978, exporta Caribe/LatAm | N27: https://www.yellowpages.com/medley-fl/medley-steel-and-supply-inc | P27: 1978 | Q27: =IFERROR(VLOOKUP(J27,Parametros!$A$5:$B$9,2,FALSE()),0) -> 1 | R27: =IFERROR(VLOOKUP(H27,Parametros!$D$5:$E$16,2,FALSE()),1) -> 2 | S27: =IF(OR(N(O27)>=Parametros!$H$9,AND(N(P27)>0,N(P27)<=Parametros!$H$10)),1,0) -> 1 | T27: =Q27+R27+S27 -> 4 | U27: =IF(OR(V27="Inactive",V27="No encontrada"),"Descartada",IF(AND(T27>=Parametros!$H$5,S27=1),"A",IF(T27>=Parametros!$H$6,"B","C"))) -> B | V27: Pendiente
A28: P024 | B28: Amigo Pallets Inc | C28: Medley | E28: Miami-Dade | F28: Fabricación/reciclaje de paletas | G28: 32 | H28: 31-33 Manufactura | I28: Inc | J28: Tiene web (auditar) | K28: Facebook; Instagram | L28: Sí | M28: Est. 2010; IG 172 seguidores | N28: https://www.facebook.com/amigopallets/ | P28: 2010 | Q28: =IFERROR(VLOOKUP(J28,Parametros!$A$5:$B$9,2,FALSE()),0) -> 1 | R28: =IFERROR(VLOOKUP(H28,Parametros!$D$5:$E$16,2,FALSE()),1) -> 2 | S28: =IF(OR(N(O28)>=Parametros!$H$9,AND(N(P28)>0,N(P28)<=Parametros!$H$10)),1,0) -> 0 | T28: =Q28+R28+S28 -> 3 | U28: =IF(OR(V28="Inactive",V28="No encontrada"),"Descartada",IF(AND(T28>=Parametros!$H$5,S28=1),"A",IF(T28>=Parametros!$H$6,"B","C"))) -> C | V28: Pendiente
A29: P025 | B29: Medley Machine Shop Inc | C29: Medley | E29: Miami-Dade | F29: Taller mecánico industrial | G29: 33 | H29: 31-33 Manufactura | I29: Inc | J29: Tiene web (auditar) | K29: Ninguna encontrada | L29: No | M29: Fundada 1994; dominio sin confirmar | N29: https://www.dnb.com/business-directory/company-profiles.medley_machine_shop_inc.b0232bd608d5d99948dd3a3504105627.html | P29: 1994 | Q29: =IFERROR(VLOOKUP(J29,Parametros!$A$5:$B$9,2,FALSE()),0) -> 1 | R29: =IFERROR(VLOOKUP(H29,Parametros!$D$5:$E$16,2,FALSE()),1) -> 2 | S29: =IF(OR(N(O29)>=Parametros!$H$9,AND(N(P29)>0,N(P29)<=Parametros!$H$10)),1,0) -> 1 | T29: =Q29+R29+S29 -> 4 | U29: =IF(OR(V29="Inactive",V29="No encontrada"),"Descartada",IF(AND(T29>=Parametros!$H$5,S29=1),"A",IF(T29>=Parametros!$H$6,"B","C"))) -> B | V29: Pendiente
A30: P026 | B30: Pablo's Machine Shop & Welding Corp | C30: Medley | E30: Miami-Dade | F30: Maquinado/soldadura industrial | G30: 81 | H30: 81 Servicios (auto, náutico, reparación) | I30: Corp | J30: Presencia desordenada | K30: Yelp | L30: Sí | M30: Incorporada 2012; dos dominios distintos | N30: https://www.yelp.com/biz/pablos-machine-shop-and-welding-corp-medley | P30: 2012 | Q30: =IFERROR(VLOOKUP(J30,Parametros!$A$5:$B$9,2,FALSE()),0) -> 2 | R30: =IFERROR(VLOOKUP(H30,Parametros!$D$5:$E$16,2,FALSE()),1) -> 2 | S30: =IF(OR(N(O30)>=Parametros!$H$9,AND(N(P30)>0,N(P30)<=Parametros!$H$10)),1,0) -> 0 | T30: =Q30+R30+S30 -> 4 | U30: =IF(OR(V30="Inactive",V30="No encontrada"),"Descartada",IF(AND(T30>=Parametros!$H$5,S30=1),"A",IF(T30>=Parametros!$H$6,"B","C"))) -> B | V30: Pendiente
A31: P027 | B31: Gondia Machine Shop | C31: Medley | E31: Miami-Dade | F31: Taller mecánico industrial | G31: 33 | H31: 31-33 Manufactura | I31: No verificado | J31: No verificado | K31: Ninguna encontrada | L31: No | M31: Solo Manta | N31: https://www.manta.com/c/mm4dqwp/gondia-machine-shop | Q31: =IFERROR(VLOOKUP(J31,Parametros!$A$5:$B$9,2,FALSE()),0) -> 1 | R31: =IFERROR(VLOOKUP(H31,Parametros!$D$5:$E$16,2,FALSE()),1) -> 2 | S31: =IF(OR(N(O31)>=Parametros!$H$9,AND(N(P31)>0,N(P31)<=Parametros!$H$10)),1,0) -> 0 | T31: =Q31+R31+S31 -> 3 | U31: =IF(OR(V31="Inactive",V31="No encontrada"),"Descartada",IF(AND(T31>=Parametros!$H$5,S31=1),"A",IF(T31>=Parametros!$H$6,"B","C"))) -> C | V31: Pendiente
A32: P028 | B32: Super Diesel Truck Repair Inc | C32: Medley | E32: Miami-Dade | F32: Reparación camiones diésel | G32: 81 | H32: 81 Servicios (auto, náutico, reparación) | I32: Inc | J32: Tiene web (auditar) | K32: Yelp; Birdeye | L32: Sí | M32: 3.5 estrellas / 13 reseñas | N32: https://www.manta.com/c/mhcrbf8/super-diesel-truck-repair-inc | Q32: =IFERROR(VLOOKUP(J32,Parametros!$A$5:$B$9,2,FALSE()),0) -> 1 | R32: =IFERROR(VLOOKUP(H32,Parametros!$D$5:$E$16,2,FALSE()),1) -> 2 | S32: =IF(OR(N(O32)>=Parametros!$H$9,AND(N(P32)>0,N(P32)<=Parametros!$H$10)),1,0) -> 0 | T32: =Q32+R32+S32 -> 3 | U32: =IF(OR(V32="Inactive",V32="No encontrada"),"Descartada",IF(AND(T32>=Parametros!$H$5,S32=1),"A",IF(T32>=Parametros!$H$6,"B","C"))) -> C | V32: Pendiente
A33: P029 | B33: LaRosa Diesel Mechanical | C33: Medley | E33: Miami-Dade | F33: Reparación camiones diésel | G33: 81 | H33: 81 Servicios (auto, náutico, reparación) | I33: No verificado | J33: No verificado | K33: Yelp | L33: Sí | M33: Solo Yelp | N33: https://www.yelp.com/biz/larosa-diesel-mechanical-medley | Q33: =IFERROR(VLOOKUP(J33,Parametros!$A$5:$B$9,2,FALSE()),0) -> 1 | R33: =IFERROR(VLOOKUP(H33,Parametros!$D$5:$E$16,2,FALSE()),1) -> 2 | S33: =IF(OR(N(O33)>=Parametros!$H$9,AND(N(P33)>0,N(P33)<=Parametros!$H$10)),1,0) -> 0 | T33: =Q33+R33+S33 -> 3 | U33: =IF(OR(V33="Inactive",V33="No encontrada"),"Descartada",IF(AND(T33>=Parametros!$H$5,S33=1),"A",IF(T33>=Parametros!$H$6,"B","C"))) -> C | V33: Pendiente
A34: P030 | B34: CYMA Truck Repair | C34: Medley | E34: Miami-Dade | F34: Reparación camiones diésel | G34: 81 | H34: 81 Servicios (auto, náutico, reparación) | I34: No verificado | J34: No verificado | K34: Yelp | L34: Sí | M34: Solo Yelp | N34: https://www.yelp.com/biz/cyma-truck-repair-medley | Q34: =IFERROR(VLOOKUP(J34,Parametros!$A$5:$B$9,2,FALSE()),0) -> 1 | R34: =IFERROR(VLOOKUP(H34,Parametros!$D$5:$E$16,2,FALSE()),1) -> 2 | S34: =IF(OR(N(O34)>=Parametros!$H$9,AND(N(P34)>0,N(P34)<=Parametros!$H$10)),1,0) -> 0 | T34: =Q34+R34+S34 -> 3 | U34: =IF(OR(V34="Inactive",V34="No encontrada"),"Descartada",IF(AND(T34>=Parametros!$H$5,S34=1),"A",IF(T34>=Parametros!$H$6,"B","C"))) -> C | V34: Pendiente
A35: P031 | B35: International Cruise Food & Hotel Suppliers Inc | C35: Medley | E35: Miami-Dade | F35: Distribución alimentaria a cruceros | G35: 42 | H35: 42 Comercio mayorista | I35: Inc | J35: Tiene web (auditar) | K35: Nextdoor; Indeed | L35: Sí | M35: Inc. 1998, almacén 200,000 ft² | N35: https://www.manta.com/c/mm21vw1/international-cruise-food-hotel-suppliers-inc | P35: 1998 | Q35: =IFERROR(VLOOKUP(J35,Parametros!$A$5:$B$9,2,FALSE()),0) -> 1 | R35: =IFERROR(VLOOKUP(H35,Parametros!$D$5:$E$16,2,FALSE()),1) -> 2 | S35: =IF(OR(N(O35)>=Parametros!$H$9,AND(N(P35)>0,N(P35)<=Parametros!$H$10)),1,0) -> 1 | T35: =Q35+R35+S35 -> 4 | U35: =IF(OR(V35="Inactive",V35="No encontrada"),"Descartada",IF(AND(T35>=Parametros!$H$5,S35=1),"A",IF(T35>=Parametros!$H$6,"B","C"))) -> B | V35: Pendiente
A36: P032 | B36: Allsteel & Gypsum Products Inc | C36: Medley | E36: Miami-Dade | F36: Distribución materiales de construcción | G36: 42 | H36: 42 Comercio mayorista | I36: Inc | J36: Sitio obsoleto | K36: Ninguna encontrada | L36: No | M36: URL /index.html: sitio estático antiguo (no confirmado) | N36: https://www.allsteelproducts.com/index.html | Q36: =IFERROR(VLOOKUP(J36,Parametros!$A$5:$B$9,2,FALSE()),0) -> 3 | R36: =IFERROR(VLOOKUP(H36,Parametros!$D$5:$E$16,2,FALSE()),1) -> 2 | S36: =IF(OR(N(O36)>=Parametros!$H$9,AND(N(P36)>0,N(P36)<=Parametros!$H$10)),1,0) -> 0 | T36: =Q36+R36+S36 -> 5 | U36: =IF(OR(V36="Inactive",V36="No encontrada"),"Descartada",IF(AND(T36>=Parametros!$H$5,S36=1),"A",IF(T36>=Parametros!$H$6,"B","C"))) -> B | V36: Pendiente
A37: P033 | B37: Structural Prestressed Industries Inc | C37: Medley | E37: Miami-Dade | F37: Prefabricados de concreto | G37: 32 | H37: 31-33 Manufactura | I37: Inc | J37: No verificado | K37: Ninguna encontrada | L37: No | M37: Est. 1996, gran prefabricadora | N37: https://buildingrenewable.com/12-best-precast-concrete-construction-companies-in-florida/ | P37: 1996 | Q37: =IFERROR(VLOOKUP(J37,Parametros!$A$5:$B$9,2,FALSE()),0) -> 1 | R37: =IFERROR(VLOOKUP(H37,Parametros!$D$5:$E$16,2,FALSE()),1) -> 2 | S37: =IF(OR(N(O37)>=Parametros!$H$9,AND(N(P37)>0,N(P37)<=Parametros!$H$10)),1,0) -> 1 | T37: =Q37+R37+S37 -> 4 | U37: =IF(OR(V37="Inactive",V37="No encontrada"),"Descartada",IF(AND(T37>=Parametros!$H$5,S37=1),"A",IF(T37>=Parametros!$H$6,"B","C"))) -> B | V37: Pendiente
A38: P034 | B38: Doral Freight Logistics Inc | C38: Doral | E38: Miami-Dade | F38: Logística - transporte | G38: 48 | H38: 48-49 Transporte y logística | I38: Inc | J38: Tiene web (auditar) | K38: Ninguna encontrada | L38: No | M38: Est. 1999, ~50 empleados, ~$9.4M | N38: https://www.manta.com/c/mm33hkb/doral-freight-logistics-inc | O38: 50 | P38: 1999 | Q38: =IFERROR(VLOOKUP(J38,Parametros!$A$5:$B$9,2,FALSE()),0) -> 1 | R38: =IFERROR(VLOOKUP(H38,Parametros!$D$5:$E$16,2,FALSE()),1) -> 3 | S38: =IF(OR(N(O38)>=Parametros!$H$9,AND(N(P38)>0,N(P38)<=Parametros!$H$10)),1,0) -> 1 | T38: =Q38+R38+S38 -> 5 | U38: =IF(OR(V38="Inactive",V38="No encontrada"),"Descartada",IF(AND(T38>=Parametros!$H$5,S38=1),"A",IF(T38>=Parametros!$H$6,"B","C"))) -> B | V38: Pendiente
A39: P035 | B39: Senaduana Freight Forwarders Inc | C39: Doral | E39: Miami-Dade | F39: Logística - freight forwarding | G39: 48 | H39: 48-49 Transporte y logística | I39: Inc | J39: Tiene web (auditar) | K39: Facebook; LinkedIn; Yelp | L39: Sí | M39: Est. 2004 | N39: https://www.manta.com/c/mmgmgjl/senaduana-freight-forwarders-inc | P39: 2004 | Q39: =IFERROR(VLOOKUP(J39,Parametros!$A$5:$B$9,2,FALSE()),0) -> 1 | R39: =IFERROR(VLOOKUP(H39,Parametros!$D$5:$E$16,2,FALSE()),1) -> 3 | S39: =IF(OR(N(O39)>=Parametros!$H$9,AND(N(P39)>0,N(P39)<=Parametros!$H$10)),1,0) -> 0 | T39: =Q39+R39+S39 -> 4 | U39: =IF(OR(V39="Inactive",V39="No encontrada"),"Descartada",IF(AND(T39>=Parametros!$H$5,S39=1),"A",IF(T39>=Parametros!$H$6,"B","C"))) -> B | V39: Pendiente
A40: P036 | B40: Conavenca Freight Forwarder LLC | C40: Doral | E40: Miami-Dade | F40: Logística - freight forwarding | G40: 48 | H40: 48-49 Transporte y logística | I40: LLC | J40: No verificado | K40: Ninguna encontrada | L40: No | M40: Solo Manta | N40: https://www.manta.com/c/mhks6tw/conavenca-freight-forwarder-llc | Q40: =IFERROR(VLOOKUP(J40,Parametros!$A$5:$B$9,2,FALSE()),0) -> 1 | R40: =IFERROR(VLOOKUP(H40,Parametros!$D$5:$E$16,2,FALSE()),1) -> 3 | S40: =IF(OR(N(O40)>=Parametros!$H$9,AND(N(P40)>0,N(P40)<=Parametros!$H$10)),1,0) -> 0 | T40: =Q40+R40+S40 -> 4 | U40: =IF(OR(V40="Inactive",V40="No encontrada"),"Descartada",IF(AND(T40>=Parametros!$H$5,S40=1),"A",IF(T40>=Parametros!$H$6,"B","C"))) -> B | V40: Pendiente
A41: P037 | B41: TMC Import & Export Co | C41: Doral | E41: Miami-Dade | F41: Import/export (embalaje y equipos) | G41: 42 | H41: 42 Comercio mayorista | I41: LLC | J41: Tiene web (auditar) | K41: Ninguna encontrada | L41: No | M41: Est. 1981, ~11 empleados, ~$2.4M | Forma legal fuente: LLC (según YP) | N41: https://www.manta.com/c/mbg66v7/tmc-import-export-co | O41: 11 | P41: 1981 | Q41: =IFERROR(VLOOKUP(J41,Parametros!$A$5:$B$9,2,FALSE()),0) -> 1 | R41: =IFERROR(VLOOKUP(H41,Parametros!$D$5:$E$16,2,FALSE()),1) -> 2 | S41: =IF(OR(N(O41)>=Parametros!$H$9,AND(N(P41)>0,N(P41)<=Parametros!$H$10)),1,0) -> 1 | T41: =Q41+R41+S41 -> 4 | U41: =IF(OR(V41="Inactive",V41="No encontrada"),"Descartada",IF(AND(T41>=Parametros!$H$5,S41=1),"A",IF(T41>=Parametros!$H$6,"B","C"))) -> B | V41: Pendiente
A42: P038 | B42: Barahona's Food Distributor LLC | C42: Doral | E42: Miami-Dade | F42: Distribución de alimentos | G42: 42 | H42: 42 Comercio mayorista | I42: LLC | J42: No verificado | K42: Ninguna encontrada | L42: No | M42: Solo Bizapedia | N42: https://www.bizapedia.com/fl/barahonas-food-distributor-llc.html | Q42: =IFERROR(VLOOKUP(J42,Parametros!$A$5:$B$9,2,FALSE()),0) -> 1 | R42: =IFERROR(VLOOKUP(H42,Parametros!$D$5:$E$16,2,FALSE()),1) -> 2 | S42: =IF(OR(N(O42)>=Parametros!$H$9,AND(N(P42)>0,N(P42)<=Parametros!$H$10)),1,0) -> 0 | T42: =Q42+R42+S42 -> 3 | U42: =IF(OR(V42="Inactive",V42="No encontrada"),"Descartada",IF(AND(T42>=Parametros!$H$5,S42=1),"A",IF(T42>=Parametros!$H$6,"B","C"))) -> C | V42: Pendiente
A43: P039 | B43: Loman Distributors Inc | C43: Doral | E43: Miami-Dade | F43: Distribución mayorista | G43: 42 | H43: 42 Comercio mayorista | I43: Inc | J43: No verificado | K43: Ninguna encontrada | L43: No | M43: Solo Bizapedia | N43: https://www.bizapedia.com/fl/loman-distributors-inc.html | Q43: =IFERROR(VLOOKUP(J43,Parametros!$A$5:$B$9,2,FALSE()),0) -> 1 | R43: =IFERROR(VLOOKUP(H43,Parametros!$D$5:$E$16,2,FALSE()),1) -> 2 | S43: =IF(OR(N(O43)>=Parametros!$H$9,AND(N(P43)>0,N(P43)<=Parametros!$H$10)),1,0) -> 0 | T43: =Q43+R43+S43 -> 3 | U43: =IF(OR(V43="Inactive",V43="No encontrada"),"Descartada",IF(AND(T43>=Parametros!$H$5,S43=1),"A",IF(T43>=Parametros!$H$6,"B","C"))) -> C | V43: Pendiente
A44: P040 | B44: K & K Dental Associates | C44: Doral | E44: Miami-Dade | F44: Clínica dental | G44: 62 | H44: 62 Salud | I44: No verificado | J44: No verificado | K44: Facebook | L44: Sí | M44: Solo Facebook | N44: https://www.facebook.com/kkdentaldoral/ | Q44: =IFERROR(VLOOKUP(J44,Parametros!$A$5:$B$9,2,FALSE()),0) -> 1 | R44: =IFERROR(VLOOKUP(H44,Parametros!$D$5:$E$16,2,FALSE()),1) -> 3 | S44: =IF(OR(N(O44)>=Parametros!$H$9,AND(N(P44)>0,N(P44)<=Parametros!$H$10)),1,0) -> 0 | T44: =Q44+R44+S44 -> 4 | U44: =IF(OR(V44="Inactive",V44="No encontrada"),"Descartada",IF(AND(T44>=Parametros!$H$5,S44=1),"A",IF(T44>=Parametros!$H$6,"B","C"))) -> B | V44: Pendiente
A45: P041 | B45: Doral Family Dental | C45: Doral | E45: Miami-Dade | F45: Clínica dental | G45: 62 | H45: 62 Salud | I45: No verificado | J45: No verificado | K45: Facebook | L45: Sí | M45: Solo Facebook | N45: https://www.facebook.com/doralfamilydentalfl/ | Q45: =IFERROR(VLOOKUP(J45,Parametros!$A$5:$B$9,2,FALSE()),0) -> 1 | R45: =IFERROR(VLOOKUP(H45,Parametros!$D$5:$E$16,2,FALSE()),1) -> 3 | S45: =IF(OR(N(O45)>=Parametros!$H$9,AND(N(P45)>0,N(P45)<=Parametros!$H$10)),1,0) -> 0 | T45: =Q45+R45+S45 -> 4 | U45: =IF(OR(V45="Inactive",V45="No encontrada"),"Descartada",IF(AND(T45>=Parametros!$H$5,S45=1),"A",IF(T45>=Parametros!$H$6,"B","C"))) -> B | V45: Pendiente
A46: P042 | B46: Brothers Produce Inc | C46: Miami (ciudad) | D46: Allapattah | E46: Miami-Dade | F46: Mayorista frutas y verduras | G46: 42 | H46: 42 Comercio mayorista | I46: Inc | J46: Tiene web (auditar) | K46: Yelp; BBB | L46: Sí | M46: Fundada 1990; sin Facebook propio | N46: https://www.bbb.org/us/fl/miami/profile/organic-food/brothers-produce-inc-0633-90067698 | P46: 1990 | Q46: =IFERROR(VLOOKUP(J46,Parametros!$A$5:$B$9,2,FALSE()),0) -> 1 | R46: =IFERROR(VLOOKUP(H46,Parametros!$D$5:$E$16,2,FALSE()),1) -> 2 | S46: =IF(OR(N(O46)>=Parametros!$H$9,AND(N(P46)>0,N(P46)<=Parametros!$H$10)),1,0) -> 1 | T46: =Q46+R46+S46 -> 4 | U46: =IF(OR(V46="Inactive",V46="No encontrada"),"Descartada",IF(AND(T46>=Parametros!$H$5,S46=1),"A",IF(T46>=Parametros!$H$6,"B","C"))) -> B | V46: Pendiente
A47: P043 | B47: 4 U Unlimited | C47: Miami (ciudad) | D47: Allapattah | E47: Miami-Dade | F47: Distribución mayorista | G47: 42 | H47: 42 Comercio mayorista | I47: No verificado | J47: No verificado | K47: Yelp | L47: Sí | M47: Solo Yelp | N47: https://www.yelp.com/biz/4-u-unlimited-miami | Q47: =IFERROR(VLOOKUP(J47,Parametros!$A$5:$B$9,2,FALSE()),0) -> 1 | R47: =IFERROR(VLOOKUP(H47,Parametros!$D$5:$E$16,2,FALSE()),1) -> 2 | S47: =IF(OR(N(O47)>=Parametros!$H$9,AND(N(P47)>0,N(P47)<=Parametros!$H$10)),1,0) -> 0 | T47: =Q47+R47+S47 -> 3 | U47: =IF(OR(V47="Inactive",V47="No encontrada"),"Descartada",IF(AND(T47>=Parametros!$H$5,S47=1),"A",IF(T47>=Parametros!$H$6,"B","C"))) -> C | V47: Pendiente
A48: P044 | B48: Excellent Fruit & Produce Inc | C48: Miami (ciudad) | D48: Allapattah | E48: Miami-Dade | F48: Mayorista frutas y verduras | G48: 42 | H48: 42 Comercio mayorista | I48: Inc | J48: Tiene web (auditar) | K48: Ninguna encontrada | L48: No | M48: Almacén refrigerado y flota propia | N48: https://excellentfruitandproduce.com/about-us/ | Q48: =IFERROR(VLOOKUP(J48,Parametros!$A$5:$B$9,2,FALSE()),0) -> 1 | R48: =IFERROR(VLOOKUP(H48,Parametros!$D$5:$E$16,2,FALSE()),1) -> 2 | S48: =IF(OR(N(O48)>=Parametros!$H$9,AND(N(P48)>0,N(P48)<=Parametros!$H$10)),1,0) -> 0 | T48: =Q48+R48+S48 -> 3 | U48: =IF(OR(V48="Inactive",V48="No encontrada"),"Descartada",IF(AND(T48>=Parametros!$H$5,S48=1),"A",IF(T48>=Parametros!$H$6,"B","C"))) -> C | V48: Pendiente
A49: P045 | B49: Martinez Distributors Inc | C49: Miami (ciudad) | D49: Allapattah | E49: Miami-Dade | F49: Mayorista carnes y mariscos | G49: 42 | H49: 42 Comercio mayorista | I49: Inc | J49: Tiene web (auditar) | K49: Facebook; Yelp | L49: Sí | M49: Desde 1997, 3 tiendas, planta USDA | N49: https://www.yelp.com/biz/martinez-distributors-miami-2 | P49: 1997 | Q49: =IFERROR(VLOOKUP(J49,Parametros!$A$5:$B$9,2,FALSE()),0) -> 1 | R49: =IFERROR(VLOOKUP(H49,Parametros!$D$5:$E$16,2,FALSE()),1) -> 2 | S49: =IF(OR(N(O49)>=Parametros!$H$9,AND(N(P49)>0,N(P49)<=Parametros!$H$10)),1,0) -> 1 | T49: =Q49+R49+S49 -> 4 | U49: =IF(OR(V49="Inactive",V49="No encontrada"),"Descartada",IF(AND(T49>=Parametros!$H$5,S49=1),"A",IF(T49>=Parametros!$H$6,"B","C"))) -> B | V49: Pendiente
A50: P046 | B50: El Rey de las Fritas | C50: Miami (ciudad) | D50: Little Havana | E50: Miami-Dade | F50: Restaurante | G50: 72 | H50: 72 Restaurantes/hotelería | I50: No verificado | J50: Tiene web (auditar) | K50: Facebook | L50: Sí | M50: Cadena local desde 1982 | N50: https://www.facebook.com/reydelasfritas/ | P50: 1982 | Q50: =IFERROR(VLOOKUP(J50,Parametros!$A$5:$B$9,2,FALSE()),0) -> 1 | R50: =IFERROR(VLOOKUP(H50,Parametros!$D$5:$E$16,2,FALSE()),1) -> 1 | S50: =IF(OR(N(O50)>=Parametros!$H$9,AND(N(P50)>0,N(P50)<=Parametros!$H$10)),1,0) -> 1 | T50: =Q50+R50+S50 -> 3 | U50: =IF(OR(V50="Inactive",V50="No encontrada"),"Descartada",IF(AND(T50>=Parametros!$H$5,S50=1),"A",IF(T50>=Parametros!$H$6,"B","C"))) -> C | V50: Pendiente
A51: P047 | B51: El Exquisito Restaurant | C51: Miami (ciudad) | D51: Little Havana | E51: Miami-Dade | F51: Restaurante | G51: 72 | H51: 72 Restaurantes/hotelería | I51: No verificado | J51: No verificado | K51: Ninguna encontrada | L51: No | M51: Familia Coro desde 1974 en Calle Ocho | N51: https://www.neighborhoods.com/blog/cuban-restaurants-in-little-havana-you-cant-miss | P51: 1974 | Q51: =IFERROR(VLOOKUP(J51,Parametros!$A$5:$B$9,2,FALSE()),0) -> 1 | R51: =IFERROR(VLOOKUP(H51,Parametros!$D$5:$E$16,2,FALSE()),1) -> 1 | S51: =IF(OR(N(O51)>=Parametros!$H$9,AND(N(P51)>0,N(P51)<=Parametros!$H$10)),1,0) -> 1 | T51: =Q51+R51+S51 -> 3 | U51: =IF(OR(V51="Inactive",V51="No encontrada"),"Descartada",IF(AND(T51>=Parametros!$H$5,S51=1),"A",IF(T51>=Parametros!$H$6,"B","C"))) -> C | V51: Pendiente
A52: P048 | B52: Kendale Air Conditioning Inc | C52: Kendall | E52: Miami-Dade | F52: HVAC | G52: 23 | H52: 23 Construcción y oficios | I52: Inc | J52: Tiene web (auditar) | K52: Facebook; LinkedIn; Yelp | L52: Sí | M52: Desde 1988; BBB 2014 | N52: https://www.bbb.org/us/fl/miami/profile/heating-and-air-conditioning/kendale-air-conditioning-0633-23009691 | P52: 1988 | Q52: =IFERROR(VLOOKUP(J52,Parametros!$A$5:$B$9,2,FALSE()),0) -> 1 | R52: =IFERROR(VLOOKUP(H52,Parametros!$D$5:$E$16,2,FALSE()),1) -> 3 | S52: =IF(OR(N(O52)>=Parametros!$H$9,AND(N(P52)>0,N(P52)<=Parametros!$H$10)),1,0) -> 1 | T52: =Q52+R52+S52 -> 5 | U52: =IF(OR(V52="Inactive",V52="No encontrada"),"Descartada",IF(AND(T52>=Parametros!$H$5,S52=1),"A",IF(T52>=Parametros!$H$6,"B","C"))) -> B | V52: Pendiente
A53: P049 | B53: Kendall South Medical Center Inc | C53: Kendall | E53: Miami-Dade | F53: Clínica médica | G53: 62 | H53: 62 Salud | I53: Inc | J53: No verificado | K53: Ninguna encontrada | L53: No | M53: Solo directorio WebMD | N53: https://doctor.webmd.com/practice/kendall-south-medical-center-inc-422a0a48-1a37-46b1-973c-95ba062d11e3 | Q53: =IFERROR(VLOOKUP(J53,Parametros!$A$5:$B$9,2,FALSE()),0) -> 1 | R53: =IFERROR(VLOOKUP(H53,Parametros!$D$5:$E$16,2,FALSE()),1) -> 3 | S53: =IF(OR(N(O53)>=Parametros!$H$9,AND(N(P53)>0,N(P53)<=Parametros!$H$10)),1,0) -> 0 | T53: =Q53+R53+S53 -> 4 | U53: =IF(OR(V53="Inactive",V53="No encontrada"),"Descartada",IF(AND(T53>=Parametros!$H$5,S53=1),"A",IF(T53>=Parametros!$H$6,"B","C"))) -> B | V53: Pendiente
A54: P050 | B54: Kendall Medical Center Inc | C54: Kendall | E54: Miami-Dade | F54: Clínica médica | G54: 62 | H54: 62 Salud | I54: Inc | J54: No verificado | K54: Ninguna encontrada | L54: No | M54: Solo directorio WebMD | N54: https://doctor.webmd.com/practice/kendall-medical-center-inc-773643c8-4703-e211-a42b-001f29e3eb44-physicians/alpha/all | Q54: =IFERROR(VLOOKUP(J54,Parametros!$A$5:$B$9,2,FALSE()),0) -> 1 | R54: =IFERROR(VLOOKUP(H54,Parametros!$D$5:$E$16,2,FALSE()),1) -> 3 | S54: =IF(OR(N(O54)>=Parametros!$H$9,AND(N(P54)>0,N(P54)<=Parametros!$H$10)),1,0) -> 0 | T54: =Q54+R54+S54 -> 4 | U54: =IF(OR(V54="Inactive",V54="No encontrada"),"Descartada",IF(AND(T54>=Parametros!$H$5,S54=1),"A",IF(T54>=Parametros!$H$6,"B","C"))) -> B | V54: Pendiente
A55: P051 | B55: Krome Auto and Tire Inc | C55: Homestead | E55: Miami-Dade | F55: Automotriz - taller/llantas | G55: 81 | H55: 81 Servicios (auto, náutico, reparación) | I55: Inc | J55: Tiene web (auditar) | K55: BBB; Yelp; Birdeye | L55: Sí | M55: Fundada 1992; 38 reseñas | N55: https://www.bbb.org/us/fl/homestead/profile/auto-repair/krome-auto-tire-svc-0633-90269976 | P55: 1992 | Q55: =IFERROR(VLOOKUP(J55,Parametros!$A$5:$B$9,2,FALSE()),0) -> 1 | R55: =IFERROR(VLOOKUP(H55,Parametros!$D$5:$E$16,2,FALSE()),1) -> 2 | S55: =IF(OR(N(O55)>=Parametros!$H$9,AND(N(P55)>0,N(P55)<=Parametros!$H$10)),1,0) -> 1 | T55: =Q55+R55+S55 -> 4 | U55: =IF(OR(V55="Inactive",V55="No encontrada"),"Descartada",IF(AND(T55>=Parametros!$H$5,S55=1),"A",IF(T55>=Parametros!$H$6,"B","C"))) -> B | V55: Pendiente
A56: P052 | B56: R Plants Inc | C56: Homestead | E56: Miami-Dade | F56: Vivero mayorista | G56: 11 | H56: 11 Agricultura/viveros | I56: Inc | J56: Tiene web (auditar) | K56: Facebook; Instagram | L56: Sí | M56: Est. 1997, 180+ acres | N56: https://www.facebook.com/rplantsinc/ | P56: 1997 | Q56: =IFERROR(VLOOKUP(J56,Parametros!$A$5:$B$9,2,FALSE()),0) -> 1 | R56: =IFERROR(VLOOKUP(H56,Parametros!$D$5:$E$16,2,FALSE()),1) -> 1 | S56: =IF(OR(N(O56)>=Parametros!$H$9,AND(N(P56)>0,N(P56)<=Parametros!$H$10)),1,0) -> 1 | T56: =Q56+R56+S56 -> 3 | U56: =IF(OR(V56="Inactive",V56="No encontrada"),"Descartada",IF(AND(T56>=Parametros!$H$5,S56=1),"A",IF(T56>=Parametros!$H$6,"B","C"))) -> C | V56: Pendiente
A57: P053 | B57: Liner Growers Nursery | C57: Homestead | E57: Miami-Dade | F57: Vivero mayorista | G57: 11 | H57: 11 Agricultura/viveros | I57: No verificado | J57: No verificado | K57: Ninguna encontrada | L57: No | M57: Solo Manta; 10+ años | N57: https://www.manta.com/c/mvvd9cj/liner-growers-nursery | Q57: =IFERROR(VLOOKUP(J57,Parametros!$A$5:$B$9,2,FALSE()),0) -> 1 | R57: =IFERROR(VLOOKUP(H57,Parametros!$D$5:$E$16,2,FALSE()),1) -> 1 | S57: =IF(OR(N(O57)>=Parametros!$H$9,AND(N(P57)>0,N(P57)<=Parametros!$H$10)),1,0) -> 0 | T57: =Q57+R57+S57 -> 2 | U57: =IF(OR(V57="Inactive",V57="No encontrada"),"Descartada",IF(AND(T57>=Parametros!$H$5,S57=1),"A",IF(T57>=Parametros!$H$6,"B","C"))) -> C | V57: Pendiente
A58: P054 | B58: Manuel Diaz Farms Inc | C58: Homestead | E58: Miami-Dade | F58: Vivero mayorista | G58: 11 | H58: 11 Agricultura/viveros | I58: Inc | J58: No verificado | K58: Ninguna encontrada | L58: No | M58: Categoría Wholesale Nurseries Manta | N58: https://www.manta.com/mb_55_B80C105M_345/nursery_stock/homestead_fl | Q58: =IFERROR(VLOOKUP(J58,Parametros!$A$5:$B$9,2,FALSE()),0) -> 1 | R58: =IFERROR(VLOOKUP(H58,Parametros!$D$5:$E$16,2,FALSE()),1) -> 1 | S58: =IF(OR(N(O58)>=Parametros!$H$9,AND(N(P58)>0,N(P58)<=Parametros!$H$10)),1,0) -> 0 | T58: =Q58+R58+S58 -> 2 | U58: =IF(OR(V58="Inactive",V58="No encontrada"),"Descartada",IF(AND(T58>=Parametros!$H$5,S58=1),"A",IF(T58>=Parametros!$H$6,"B","C"))) -> C | V58: Pendiente
A59: P055 | B59: Quality Growers Inc | C59: Homestead | E59: Miami-Dade | F59: Vivero mayorista | G59: 11 | H59: 11 Agricultura/viveros | I59: Inc | J59: No verificado | K59: Ninguna encontrada | L59: No | M59: Categoría Wholesale Nurseries Manta | N59: https://www.manta.com/mb_55_B80C105M_345/nursery_stock/homestead_fl | Q59: =IFERROR(VLOOKUP(J59,Parametros!$A$5:$B$9,2,FALSE()),0) -> 1 | R59: =IFERROR(VLOOKUP(H59,Parametros!$D$5:$E$16,2,FALSE()),1) -> 1 | S59: =IF(OR(N(O59)>=Parametros!$H$9,AND(N(P59)>0,N(P59)<=Parametros!$H$10)),1,0) -> 0 | T59: =Q59+R59+S59 -> 2 | U59: =IF(OR(V59="Inactive",V59="No encontrada"),"Descartada",IF(AND(T59>=Parametros!$H$5,S59=1),"A",IF(T59>=Parametros!$H$6,"B","C"))) -> C | V59: Pendiente
A60: P056 | B60: Medallion Nurseries | C60: Homestead | E60: Miami-Dade | F60: Vivero mayorista | G60: 11 | H60: 11 Agricultura/viveros | I60: No verificado | J60: No verificado | K60: Ninguna encontrada | L60: No | M60: Categoría Wholesale Nurseries Manta | N60: https://www.manta.com/mb_55_B80C105M_345/nursery_stock/homestead_fl | Q60: =IFERROR(VLOOKUP(J60,Parametros!$A$5:$B$9,2,FALSE()),0) -> 1 | R60: =IFERROR(VLOOKUP(H60,Parametros!$D$5:$E$16,2,FALSE()),1) -> 1 | S60: =IF(OR(N(O60)>=Parametros!$H$9,AND(N(P60)>0,N(P60)<=Parametros!$H$10)),1,0) -> 0 | T60: =Q60+R60+S60 -> 2 | U60: =IF(OR(V60="Inactive",V60="No encontrada"),"Descartada",IF(AND(T60>=Parametros!$H$5,S60=1),"A",IF(T60>=Parametros!$H$6,"B","C"))) -> C | V60: Pendiente
A61: P057 | B61: Sam S. Accursio & Sons Farms | C61: Homestead | E61: Miami-Dade | F61: Agricultura/empacadora | G61: 11 | H61: 11 Agricultura/viveros | I61: No verificado | J61: No verificado | K61: Ninguna encontrada | L61: No | M61: Desde 1948, empacadora propia | N61: https://ediblesouthflorida.ediblecommunities.com/eat/fresh-demand-local-produce-longtime-homestead-farm/ | P61: 1948 | Q61: =IFERROR(VLOOKUP(J61,Parametros!$A$5:$B$9,2,FALSE()),0) -> 1 | R61: =IFERROR(VLOOKUP(H61,Parametros!$D$5:$E$16,2,FALSE()),1) -> 1 | S61: =IF(OR(N(O61)>=Parametros!$H$9,AND(N(P61)>0,N(P61)<=Parametros!$H$10)),1,0) -> 1 | T61: =Q61+R61+S61 -> 3 | U61: =IF(OR(V61="Inactive",V61="No encontrada"),"Descartada",IF(AND(T61>=Parametros!$H$5,S61=1),"A",IF(T61>=Parametros!$H$6,"B","C"))) -> C | V61: Pendiente
A62: P058 | B62: Sudsies Dry Cleaners | C62: Miami Beach | E62: Miami-Dade | F62: Tintorería | G62: 81 | H62: 81 Servicios (auto, náutico, reparación) | I62: No verificado | J62: No verificado | K62: Yelp | L62: Sí | M62: Est. 1996; 244 reseñas Yelp | N62: https://www.yelp.com/biz/sudsies-dry-cleaners-miami-beach | P62: 1996 | Q62: =IFERROR(VLOOKUP(J62,Parametros!$A$5:$B$9,2,FALSE()),0) -> 1 | R62: =IFERROR(VLOOKUP(H62,Parametros!$D$5:$E$16,2,FALSE()),1) -> 2 | S62: =IF(OR(N(O62)>=Parametros!$H$9,AND(N(P62)>0,N(P62)<=Parametros!$H$10)),1,0) -> 1 | T62: =Q62+R62+S62 -> 4 | U62: =IF(OR(V62="Inactive",V62="No encontrada"),"Descartada",IF(AND(T62>=Parametros!$H$5,S62=1),"A",IF(T62>=Parametros!$H$6,"B","C"))) -> B | V62: Pendiente
A63: P059 | B63: Complete Yacht Service | C63: Fort Lauderdale | E63: Broward | F63: Náutico - motores/partes y servicio | G63: 81 | H63: 81 Servicios (auto, náutico, reparación) | I63: Inc | J63: Sin sitio web | K63: Facebook; Yelp | L63: Sí | M63: Est. 1976, ~6 empleados, ~$1.3M ventas (Manta); búsqueda por nombre solo devuelve Facebook/Yelp | Forma legal fuente: Inc (Manta; no verificado en Sunbiz) | N63: https://www.yelp.com/biz/complete-yacht-service-fort-lauderdale | O63: 6 | P63: 1976 | Q63: =IFERROR(VLOOKUP(J63,Parametros!$A$5:$B$9,2,FALSE()),0) -> 3 | R63: =IFERROR(VLOOKUP(H63,Parametros!$D$5:$E$16,2,FALSE()),1) -> 2 | S63: =IF(OR(N(O63)>=Parametros!$H$9,AND(N(P63)>0,N(P63)<=Parametros!$H$10)),1,0) -> 1 | T63: =Q63+R63+S63 -> 6 | U63: =IF(OR(V63="Inactive",V63="No encontrada"),"Descartada",IF(AND(T63>=Parametros!$H$5,S63=1),"A",IF(T63>=Parametros!$H$6,"B","C"))) -> A | V63: Active
A64: P060 | B64: Superior Stainless & Yacht Repair | C64: Fort Lauderdale | E64: Broward | F64: Náutico - soldadura/inox yates | G64: 81 | H64: 81 Servicios (auto, náutico, reparación) | I64: No verificado | J64: Sin sitio web | K64: Ninguna encontrada | L64: No | M64: BBB A+, desde 1993; solo directorios | N64: https://www.bbb.org/us/fl/ft-lauderdale/profile/boat-repair/superior-stainless-yacht-repair-0633-11011513 | P64: 1993 | Q64: =IFERROR(VLOOKUP(J64,Parametros!$A$5:$B$9,2,FALSE()),0) -> 3 | R64: =IFERROR(VLOOKUP(H64,Parametros!$D$5:$E$16,2,FALSE()),1) -> 2 | S64: =IF(OR(N(O64)>=Parametros!$H$9,AND(N(P64)>0,N(P64)<=Parametros!$H$10)),1,0) -> 1 | T64: =Q64+R64+S64 -> 6 | U64: =IF(OR(V64="Inactive",V64="No encontrada"),"Descartada",IF(AND(T64>=Parametros!$H$5,S64=1),"A",IF(T64>=Parametros!$H$6,"B","C"))) -> A | V64: Pendiente
A65: P061 | B65: Top Quality Yachts Refinishing & Refurbishing | C65: Fort Lauderdale | E65: Broward | F65: Náutico - pintura/refinish yates | G65: 81 | H65: 81 Servicios (auto, náutico, reparación) | I65: No verificado | J65: Sin sitio web | K65: Ninguna encontrada | L65: No | M65: BBB, desde 1999; búsqueda por nombre solo devuelve BBB | N65: https://www.bbb.org/us/fl/fort-lauderdale/profile/boat-repair/top-quality-yachts-refinishing-refurbishing-0633-4006026 | P65: 1999 | Q65: =IFERROR(VLOOKUP(J65,Parametros!$A$5:$B$9,2,FALSE()),0) -> 3 | R65: =IFERROR(VLOOKUP(H65,Parametros!$D$5:$E$16,2,FALSE()),1) -> 2 | S65: =IF(OR(N(O65)>=Parametros!$H$9,AND(N(P65)>0,N(P65)<=Parametros!$H$10)),1,0) -> 1 | T65: =Q65+R65+S65 -> 6 | U65: =IF(OR(V65="Inactive",V65="No encontrada"),"Descartada",IF(AND(T65>=Parametros!$H$5,S65=1),"A",IF(T65>=Parametros!$H$6,"B","C"))) -> A | V65: Pendiente
A66: P062 | B66: Complete Yacht Care Inc | C66: Fort Lauderdale | E66: Broward | F66: Náutico - mantenimiento yates | G66: 81 | H66: 81 Servicios (auto, náutico, reparación) | I66: Inc | J66: Sin sitio web | K66: Ninguna encontrada | L66: No | M66: Fundada 2006; solo Manta y D&B | N66: https://www.manta.com/c/mmn3jvb/complete-yacht-care-inc | P66: 2006 | Q66: =IFERROR(VLOOKUP(J66,Parametros!$A$5:$B$9,2,FALSE()),0) -> 3 | R66: =IFERROR(VLOOKUP(H66,Parametros!$D$5:$E$16,2,FALSE()),1) -> 2 | S66: =IF(OR(N(O66)>=Parametros!$H$9,AND(N(P66)>0,N(P66)<=Parametros!$H$10)),1,0) -> 0 | T66: =Q66+R66+S66 -> 5 | U66: =IF(OR(V66="Inactive",V66="No encontrada"),"Descartada",IF(AND(T66>=Parametros!$H$5,S66=1),"A",IF(T66>=Parametros!$H$6,"B","C"))) -> B | V66: Pendiente
A67: P063 | B67: Ship Side Service Inc | C67: Fort Lauderdale | E67: Broward | F67: Náutico - servicios a yates | G67: 81 | H67: 81 Servicios (auto, náutico, reparación) | I67: Inc | J67: Sin sitio web | K67: Ninguna encontrada | L67: No | M67: BBB A+, ~22 años; registro estatal muestra CANCEL ADM DISS/REV: verificar en Sunbiz | Forma legal fuente: Inc (posible Admin. Dissolved) | N67: https://www.bbb.org/us/fl/fort-lauderdale/profile/boat-repair/ship-side-service-0633-22003092 | Q67: =IFERROR(VLOOKUP(J67,Parametros!$A$5:$B$9,2,FALSE()),0) -> 3 | R67: =IFERROR(VLOOKUP(H67,Parametros!$D$5:$E$16,2,FALSE()),1) -> 2 | S67: =IF(OR(N(O67)>=Parametros!$H$9,AND(N(P67)>0,N(P67)<=Parametros!$H$10)),1,0) -> 0 | T67: =Q67+R67+S67 -> 5 | U67: =IF(OR(V67="Inactive",V67="No encontrada"),"Descartada",IF(AND(T67>=Parametros!$H$5,S67=1),"A",IF(T67>=Parametros!$H$6,"B","C"))) -> Descartada | V67: Inactive
A68: P064 | B68: Shoreline Marine LLC | C68: Pompano Beach | E68: Broward | F68: Náutico - reparación/refit | G68: 81 | H68: 81 Servicios (auto, náutico, reparación) | I68: LLC | J68: Sin sitio web | K68: Facebook | L68: Sí | M68: Desde 2014; ficha Yelp no reclamada | Forma legal fuente: LLC (BBB) | N68: https://www.yelp.com/biz/shoreline-marine-pompano-beach | P68: 2014 | Q68: =IFERROR(VLOOKUP(J68,Parametros!$A$5:$B$9,2,FALSE()),0) -> 3 | R68: =IFERROR(VLOOKUP(H68,Parametros!$D$5:$E$16,2,FALSE()),1) -> 2 | S68: =IF(OR(N(O68)>=Parametros!$H$9,AND(N(P68)>0,N(P68)<=Parametros!$H$10)),1,0) -> 0 | T68: =Q68+R68+S68 -> 5 | U68: =IF(OR(V68="Inactive",V68="No encontrada"),"Descartada",IF(AND(T68>=Parametros!$H$5,S68=1),"A",IF(T68>=Parametros!$H$6,"B","C"))) -> B | V68: Pendiente
A69: P065 | B69: Yacht Mechanics of Florida | C69: Fort Lauderdale | E69: Broward | F69: Náutico - mecánica/hidráulica | G69: 81 | H69: 81 Servicios (auto, náutico, reparación) | I69: No verificado | J69: Sitio obsoleto | K69: Yelp; BBB | L69: Sí | M69: 42 años; sitio básico + página Genially: candidato a rediseño | N69: https://www.yelp.com/biz/yacht-mechanics-of-florida-fort-lauderdale | Q69: =IFERROR(VLOOKUP(J69,Parametros!$A$5:$B$9,2,FALSE()),0) -> 3 | R69: =IFERROR(VLOOKUP(H69,Parametros!$D$5:$E$16,2,FALSE()),1) -> 2 | S69: =IF(OR(N(O69)>=Parametros!$H$9,AND(N(P69)>0,N(P69)<=Parametros!$H$10)),1,0) -> 0 | T69: =Q69+R69+S69 -> 5 | U69: =IF(OR(V69="Inactive",V69="No encontrada"),"Descartada",IF(AND(T69>=Parametros!$H$5,S69=1),"A",IF(T69>=Parametros!$H$6,"B","C"))) -> B | V69: Pendiente
A70: P066 | B70: Land & Sea Air Conditioning of South Florida Inc | C70: Davie | E70: Broward | F70: HVAC | G70: 23 | H70: 23 Construcción y oficios | I70: Inc | J70: Sin sitio web | K70: Facebook; Yelp | L70: Sí | M70: Desde 2008; solo directorios y Facebook | N70: https://www.manta.com/c/mb5d3rb/land-sea-air-conditioning-of | P70: 2008 | Q70: =IFERROR(VLOOKUP(J70,Parametros!$A$5:$B$9,2,FALSE()),0) -> 3 | R70: =IFERROR(VLOOKUP(H70,Parametros!$D$5:$E$16,2,FALSE()),1) -> 3 | S70: =IF(OR(N(O70)>=Parametros!$H$9,AND(N(P70)>0,N(P70)<=Parametros!$H$10)),1,0) -> 0 | T70: =Q70+R70+S70 -> 6 | U70: =IF(OR(V70="Inactive",V70="No encontrada"),"Descartada",IF(AND(T70>=Parametros!$H$5,S70=1),"A",IF(T70>=Parametros!$H$6,"B","C"))) -> B | V70: Pendiente
A71: P067 | B71: Million Air Conditioning Corp | C71: Davie | E71: Broward | F71: HVAC | G71: 23 | H71: 23 Construcción y oficios | I71: Corp | J71: Sin sitio web | K71: Ninguna encontrada | L71: No | M71: Est. 2006, ~3 empleados; contratista certificado DBPR | N71: https://www.manta.com/c/mmym5vw/million-air-conditioning-corporation | O71: 3 | P71: 2006 | Q71: =IFERROR(VLOOKUP(J71,Parametros!$A$5:$B$9,2,FALSE()),0) -> 3 | R71: =IFERROR(VLOOKUP(H71,Parametros!$D$5:$E$16,2,FALSE()),1) -> 3 | S71: =IF(OR(N(O71)>=Parametros!$H$9,AND(N(P71)>0,N(P71)<=Parametros!$H$10)),1,0) -> 0 | T71: =Q71+R71+S71 -> 6 | U71: =IF(OR(V71="Inactive",V71="No encontrada"),"Descartada",IF(AND(T71>=Parametros!$H$5,S71=1),"A",IF(T71>=Parametros!$H$6,"B","C"))) -> B | V71: Pendiente
A72: P068 | B72: First Class Air Conditioning & Appliance Inc | C72: Davie | E72: Broward | F72: HVAC/electrodomésticos | G72: 81 | H72: 81 Servicios (auto, náutico, reparación) | I72: Inc | J72: Presencia desordenada | K72: Facebook; Yelp; Nextdoor | L72: Sí | M72: 14+ años; fichas duplicadas, sin dominio propio claro | N72: https://www.bbb.org/us/fl/davie/profile/major-appliance-services/first-class-air-conditioning-appliance-inc-0633-90137525 | Q72: =IFERROR(VLOOKUP(J72,Parametros!$A$5:$B$9,2,FALSE()),0) -> 2 | R72: =IFERROR(VLOOKUP(H72,Parametros!$D$5:$E$16,2,FALSE()),1) -> 2 | S72: =IF(OR(N(O72)>=Parametros!$H$9,AND(N(P72)>0,N(P72)<=Parametros!$H$10)),1,0) -> 0 | T72: =Q72+R72+S72 -> 4 | U72: =IF(OR(V72="Inactive",V72="No encontrada"),"Descartada",IF(AND(T72>=Parametros!$H$5,S72=1),"A",IF(T72>=Parametros!$H$6,"B","C"))) -> B | V72: Pendiente
A73: P069 | B73: Pompano Beach Texaco | C73: Pompano Beach | E73: Broward | F73: Automotriz - taller/estación | G73: 81 | H73: 81 Servicios (auto, náutico, reparación) | I73: No verificado | J73: Sin sitio web | K73: Ninguna encontrada | L73: No | M73: BBB: desde 1987 | N73: https://www.bbb.org/us/fl/pompano-beach/profile/auto-repair/pompano-beach-texaco-0633-35000319 | P73: 1987 | Q73: =IFERROR(VLOOKUP(J73,Parametros!$A$5:$B$9,2,FALSE()),0) -> 3 | R73: =IFERROR(VLOOKUP(H73,Parametros!$D$5:$E$16,2,FALSE()),1) -> 2 | S73: =IF(OR(N(O73)>=Parametros!$H$9,AND(N(P73)>0,N(P73)<=Parametros!$H$10)),1,0) -> 1 | T73: =Q73+R73+S73 -> 6 | U73: =IF(OR(V73="Inactive",V73="No encontrada"),"Descartada",IF(AND(T73>=Parametros!$H$5,S73=1),"A",IF(T73>=Parametros!$H$6,"B","C"))) -> A | V73: Pendiente
A74: P070 | B74: Our Shop Auto Repairs Inc | C74: Pompano Beach | E74: Broward | F74: Automotriz - taller | G74: 81 | H74: 81 Servicios (auto, náutico, reparación) | I74: Inc | J74: Sitio obsoleto | K74: Facebook (x2); Yelp | L74: Sí | M74: Desde 2009; sitio .us básico y Facebook duplicado | N74: https://www.bbb.org/us/fl/pompano-beach/profile/mobile-auto-repair/our-shop-auto-repairs-inc-0633-90426905 | P74: 2009 | Q74: =IFERROR(VLOOKUP(J74,Parametros!$A$5:$B$9,2,FALSE()),0) -> 3 | R74: =IFERROR(VLOOKUP(H74,Parametros!$D$5:$E$16,2,FALSE()),1) -> 2 | S74: =IF(OR(N(O74)>=Parametros!$H$9,AND(N(P74)>0,N(P74)<=Parametros!$H$10)),1,0) -> 0 | T74: =Q74+R74+S74 -> 5 | U74: =IF(OR(V74="Inactive",V74="No encontrada"),"Descartada",IF(AND(T74>=Parametros!$H$5,S74=1),"A",IF(T74>=Parametros!$H$6,"B","C"))) -> B | V74: Pendiente
A75: P071 | B75: Fast Lane Auto Repairs | C75: Pompano Beach | E75: Broward | F75: Automotriz - taller | G75: 81 | H75: 81 Servicios (auto, náutico, reparación) | I75: No verificado | J75: No verificado | K75: No verificado | L75: No verificado | M75: Solo listado BBB | N75: https://www.bbb.org/us/fl/pompano-beach/profile/auto-repair/fast-lane-auto-repairs-0633-90409985 | Q75: =IFERROR(VLOOKUP(J75,Parametros!$A$5:$B$9,2,FALSE()),0) -> 1 | R75: =IFERROR(VLOOKUP(H75,Parametros!$D$5:$E$16,2,FALSE()),1) -> 2 | S75: =IF(OR(N(O75)>=Parametros!$H$9,AND(N(P75)>0,N(P75)<=Parametros!$H$10)),1,0) -> 0 | T75: =Q75+R75+S75 -> 3 | U75: =IF(OR(V75="Inactive",V75="No encontrada"),"Descartada",IF(AND(T75>=Parametros!$H$5,S75=1),"A",IF(T75>=Parametros!$H$6,"B","C"))) -> C | V75: Pendiente
A76: P072 | B76: The Auto Spot | C76: Pompano Beach | E76: Broward | F76: Automotriz - taller | G76: 81 | H76: 81 Servicios (auto, náutico, reparación) | I76: No verificado | J76: No verificado | K76: No verificado | L76: No verificado | M76: Solo listado BBB | N76: https://www.bbb.org/us/fl/pompano-beach/profile/auto-repair/the-auto-spot-0633-90092971 | Q76: =IFERROR(VLOOKUP(J76,Parametros!$A$5:$B$9,2,FALSE()),0) -> 1 | R76: =IFERROR(VLOOKUP(H76,Parametros!$D$5:$E$16,2,FALSE()),1) -> 2 | S76: =IF(OR(N(O76)>=Parametros!$H$9,AND(N(P76)>0,N(P76)<=Parametros!$H$10)),1,0) -> 0 | T76: =Q76+R76+S76 -> 3 | U76: =IF(OR(V76="Inactive",V76="No encontrada"),"Descartada",IF(AND(T76>=Parametros!$H$5,S76=1),"A",IF(T76>=Parametros!$H$6,"B","C"))) -> C | V76: Pendiente
A77: P073 | B77: Original Look | C77: Pompano Beach | E77: Broward | F77: Automotriz - carrocería | G77: 81 | H77: 81 Servicios (auto, náutico, reparación) | I77: No verificado | J77: No verificado | K77: No verificado | L77: No verificado | M77: Solo listado BBB | N77: https://www.bbb.org/us/fl/pompano-beach/profile/auto-repair/original-look-0633-90132733 | Q77: =IFERROR(VLOOKUP(J77,Parametros!$A$5:$B$9,2,FALSE()),0) -> 1 | R77: =IFERROR(VLOOKUP(H77,Parametros!$D$5:$E$16,2,FALSE()),1) -> 2 | S77: =IF(OR(N(O77)>=Parametros!$H$9,AND(N(P77)>0,N(P77)<=Parametros!$H$10)),1,0) -> 0 | T77: =Q77+R77+S77 -> 3 | U77: =IF(OR(V77="Inactive",V77="No encontrada"),"Descartada",IF(AND(T77>=Parametros!$H$5,S77=1),"A",IF(T77>=Parametros!$H$6,"B","C"))) -> C | V77: Pendiente
A78: P074 | B78: Marina Road Boat Yard | C78: Fort Lauderdale | E78: Broward | F78: Náutico - boatyard | G78: 81 | H78: 81 Servicios (auto, náutico, reparación) | I78: No verificado | J78: No verificado | K78: No verificado | L78: No verificado | M78: Listado Manta | N78: https://www.manta.com/c/mh1g76d/marina-road-boat-yard | Q78: =IFERROR(VLOOKUP(J78,Parametros!$A$5:$B$9,2,FALSE()),0) -> 1 | R78: =IFERROR(VLOOKUP(H78,Parametros!$D$5:$E$16,2,FALSE()),1) -> 2 | S78: =IF(OR(N(O78)>=Parametros!$H$9,AND(N(P78)>0,N(P78)<=Parametros!$H$10)),1,0) -> 0 | T78: =Q78+R78+S78 -> 3 | U78: =IF(OR(V78="Inactive",V78="No encontrada"),"Descartada",IF(AND(T78>=Parametros!$H$5,S78=1),"A",IF(T78>=Parametros!$H$6,"B","C"))) -> C | V78: Pendiente
A79: P075 | B79: Yachting Bliss | C79: Pompano Beach | E79: Broward | F79: Náutico - reparación | G79: 81 | H79: 81 Servicios (auto, náutico, reparación) | I79: No verificado | J79: No verificado | K79: No verificado | L79: No verificado | M79: Listado Manta | N79: https://www.manta.com/c/mm0jvj4/yachting-bliss | Q79: =IFERROR(VLOOKUP(J79,Parametros!$A$5:$B$9,2,FALSE()),0) -> 1 | R79: =IFERROR(VLOOKUP(H79,Parametros!$D$5:$E$16,2,FALSE()),1) -> 2 | S79: =IF(OR(N(O79)>=Parametros!$H$9,AND(N(P79)>0,N(P79)<=Parametros!$H$10)),1,0) -> 0 | T79: =Q79+R79+S79 -> 3 | U79: =IF(OR(V79="Inactive",V79="No encontrada"),"Descartada",IF(AND(T79>=Parametros!$H$5,S79=1),"A",IF(T79>=Parametros!$H$6,"B","C"))) -> C | V79: Pendiente
A80: P076 | B80: Elite Yachting Solutions LLC | C80: Pompano Beach | E80: Broward | F80: Náutico - servicios | G80: 81 | H80: 81 Servicios (auto, náutico, reparación) | I80: LLC | J80: No verificado | K80: No verificado | L80: No verificado | M80: Listado Manta | N80: https://www.manta.com/c/mkhwx2k/elite-yachting-solutions-llc | Q80: =IFERROR(VLOOKUP(J80,Parametros!$A$5:$B$9,2,FALSE()),0) -> 1 | R80: =IFERROR(VLOOKUP(H80,Parametros!$D$5:$E$16,2,FALSE()),1) -> 2 | S80: =IF(OR(N(O80)>=Parametros!$H$9,AND(N(P80)>0,N(P80)<=Parametros!$H$10)),1,0) -> 0 | T80: =Q80+R80+S80 -> 3 | U80: =IF(OR(V80="Inactive",V80="No encontrada"),"Descartada",IF(AND(T80>=Parametros!$H$5,S80=1),"A",IF(T80>=Parametros!$H$6,"B","C"))) -> C | V80: Pendiente
A81: P077 | B81: S.A. Marine Services LLC | C81: Pompano Beach | E81: Broward | F81: Náutico - boat lifts | G81: 23 | H81: 23 Construcción y oficios | I81: LLC | J81: No verificado | K81: No verificado | L81: No verificado | M81: Boat lifts en Palm Beach, Broward y Miami-Dade | N81: https://www.manta.com/c/m1xl2v5/s-a-marine-services-llc | Q81: =IFERROR(VLOOKUP(J81,Parametros!$A$5:$B$9,2,FALSE()),0) -> 1 | R81: =IFERROR(VLOOKUP(H81,Parametros!$D$5:$E$16,2,FALSE()),1) -> 3 | S81: =IF(OR(N(O81)>=Parametros!$H$9,AND(N(P81)>0,N(P81)<=Parametros!$H$10)),1,0) -> 0 | T81: =Q81+R81+S81 -> 4 | U81: =IF(OR(V81="Inactive",V81="No encontrada"),"Descartada",IF(AND(T81>=Parametros!$H$5,S81=1),"A",IF(T81>=Parametros!$H$6,"B","C"))) -> B | V81: Pendiente
A82: P078 | B82: All Power Marine Boat Lifts & Docks | C82: Pompano Beach | E82: Broward | F82: Náutico - lifts/docks | G82: 23 | H82: 23 Construcción y oficios | I82: No verificado | J82: No verificado | K82: No verificado | L82: No verificado | M82: Listado Manta | N82: https://www.manta.com/c/mm7f0xx/all-power-marine-boat-lifts-docks | Q82: =IFERROR(VLOOKUP(J82,Parametros!$A$5:$B$9,2,FALSE()),0) -> 1 | R82: =IFERROR(VLOOKUP(H82,Parametros!$D$5:$E$16,2,FALSE()),1) -> 3 | S82: =IF(OR(N(O82)>=Parametros!$H$9,AND(N(P82)>0,N(P82)<=Parametros!$H$10)),1,0) -> 0 | T82: =Q82+R82+S82 -> 4 | U82: =IF(OR(V82="Inactive",V82="No encontrada"),"Descartada",IF(AND(T82>=Parametros!$H$5,S82=1),"A",IF(T82>=Parametros!$H$6,"B","C"))) -> B | V82: Pendiente
A83: P079 | B83: T&D Air Conditioning Inc | C83: Davie | E83: Broward | F83: HVAC | G83: 23 | H83: 23 Construcción y oficios | I83: Inc | J83: No verificado | K83: No verificado | L83: No verificado | M83: Manta: 30+ años | N83: https://www.manta.com/c/mr4tgvc/t-d-air-conditioning-inc | Q83: =IFERROR(VLOOKUP(J83,Parametros!$A$5:$B$9,2,FALSE()),0) -> 1 | R83: =IFERROR(VLOOKUP(H83,Parametros!$D$5:$E$16,2,FALSE()),1) -> 3 | S83: =IF(OR(N(O83)>=Parametros!$H$9,AND(N(P83)>0,N(P83)<=Parametros!$H$10)),1,0) -> 0 | T83: =Q83+R83+S83 -> 4 | U83: =IF(OR(V83="Inactive",V83="No encontrada"),"Descartada",IF(AND(T83>=Parametros!$H$5,S83=1),"A",IF(T83>=Parametros!$H$6,"B","C"))) -> B | V83: Pendiente
A84: P080 | B84: CV AC Expert LLC | C84: Davie | E84: Broward | F84: HVAC | G84: 23 | H84: 23 Construcción y oficios | I84: LLC | J84: No verificado | K84: No verificado | L84: No verificado | M84: Listado Manta | N84: https://www.manta.com/c/mhw02tp/cv-ac-expert-llc | Q84: =IFERROR(VLOOKUP(J84,Parametros!$A$5:$B$9,2,FALSE()),0) -> 1 | R84: =IFERROR(VLOOKUP(H84,Parametros!$D$5:$E$16,2,FALSE()),1) -> 3 | S84: =IF(OR(N(O84)>=Parametros!$H$9,AND(N(P84)>0,N(P84)<=Parametros!$H$10)),1,0) -> 0 | T84: =Q84+R84+S84 -> 4 | U84: =IF(OR(V84="Inactive",V84="No encontrada"),"Descartada",IF(AND(T84>=Parametros!$H$5,S84=1),"A",IF(T84>=Parametros!$H$6,"B","C"))) -> B | V84: Pendiente
A85: P081 | B85: Ocean Freight Link | C85: Miramar | E85: Broward | F85: Logística - freight forwarding | G85: 48 | H85: 48-49 Transporte y logística | I85: No verificado | J85: No verificado | K85: No verificado | L85: No verificado | M85: Manta: ~$2.5M ventas, ~6 empleados | N85: https://www.manta.com/c/mtq3wsd/ocean-freight-link | O85: 6 | Q85: =IFERROR(VLOOKUP(J85,Parametros!$A$5:$B$9,2,FALSE()),0) -> 1 | R85: =IFERROR(VLOOKUP(H85,Parametros!$D$5:$E$16,2,FALSE()),1) -> 3 | S85: =IF(OR(N(O85)>=Parametros!$H$9,AND(N(P85)>0,N(P85)<=Parametros!$H$10)),1,0) -> 0 | T85: =Q85+R85+S85 -> 4 | U85: =IF(OR(V85="Inactive",V85="No encontrada"),"Descartada",IF(AND(T85>=Parametros!$H$5,S85=1),"A",IF(T85>=Parametros!$H$6,"B","C"))) -> B | V85: Pendiente
A86: P082 | B86: Promptus LLC | C86: Miramar | E86: Broward | F86: Logística - freight forwarding | G86: 48 | H86: 48-49 Transporte y logística | I86: LLC | J86: No verificado | K86: No verificado | L86: No verificado | M86: Listado Manta | N86: https://www.manta.com/c/mmfvqs5/promptus-llc | Q86: =IFERROR(VLOOKUP(J86,Parametros!$A$5:$B$9,2,FALSE()),0) -> 1 | R86: =IFERROR(VLOOKUP(H86,Parametros!$D$5:$E$16,2,FALSE()),1) -> 3 | S86: =IF(OR(N(O86)>=Parametros!$H$9,AND(N(P86)>0,N(P86)<=Parametros!$H$10)),1,0) -> 0 | T86: =Q86+R86+S86 -> 4 | U86: =IF(OR(V86="Inactive",V86="No encontrada"),"Descartada",IF(AND(T86>=Parametros!$H$5,S86=1),"A",IF(T86>=Parametros!$H$6,"B","C"))) -> B | V86: Pendiente
A87: P083 | B87: R K A Xpress Inc | C87: Miramar | E87: Broward | F87: Logística - transporte | G87: 48 | H87: 48-49 Transporte y logística | I87: Inc | J87: No verificado | K87: No verificado | L87: No verificado | M87: Listado Manta | N87: https://www.manta.com/c/mtry58n/r-k-a-xpress-inc | Q87: =IFERROR(VLOOKUP(J87,Parametros!$A$5:$B$9,2,FALSE()),0) -> 1 | R87: =IFERROR(VLOOKUP(H87,Parametros!$D$5:$E$16,2,FALSE()),1) -> 3 | S87: =IF(OR(N(O87)>=Parametros!$H$9,AND(N(P87)>0,N(P87)<=Parametros!$H$10)),1,0) -> 0 | T87: =Q87+R87+S87 -> 4 | U87: =IF(OR(V87="Inactive",V87="No encontrada"),"Descartada",IF(AND(T87>=Parametros!$H$5,S87=1),"A",IF(T87>=Parametros!$H$6,"B","C"))) -> B | V87: Pendiente
A88: P084 | B88: J J Freight Brokerage Inc | C88: Miramar | E88: Broward | F88: Logística - broker de carga | G88: 48 | H88: 48-49 Transporte y logística | I88: Inc | J88: No verificado | K88: No verificado | L88: No verificado | M88: Listado Manta | N88: https://www.manta.com/c/mt4210t/j-j-freight-brokerage-inc | Q88: =IFERROR(VLOOKUP(J88,Parametros!$A$5:$B$9,2,FALSE()),0) -> 1 | R88: =IFERROR(VLOOKUP(H88,Parametros!$D$5:$E$16,2,FALSE()),1) -> 3 | S88: =IF(OR(N(O88)>=Parametros!$H$9,AND(N(P88)>0,N(P88)<=Parametros!$H$10)),1,0) -> 0 | T88: =Q88+R88+S88 -> 4 | U88: =IF(OR(V88="Inactive",V88="No encontrada"),"Descartada",IF(AND(T88>=Parametros!$H$5,S88=1),"A",IF(T88>=Parametros!$H$6,"B","C"))) -> B | V88: Pendiente
A89: P085 | B89: Markon Realty And Management Inc | C89: Sunrise | E89: Broward | F89: Administración de propiedades | G89: 53 | H89: 53 Inmobiliario/admin. propiedades | I89: Inc | J89: No verificado | K89: No verificado | L89: No verificado | M89: Manta: est. 1990, ~11 empleados, ~$750k | N89: https://www.manta.com/c/mm08mz3/markon-realty-and-management-inc | O89: 11 | Q89: =IFERROR(VLOOKUP(J89,Parametros!$A$5:$B$9,2,FALSE()),0) -> 1 | R89: =IFERROR(VLOOKUP(H89,Parametros!$D$5:$E$16,2,FALSE()),1) -> 2 | S89: =IF(OR(N(O89)>=Parametros!$H$9,AND(N(P89)>0,N(P89)<=Parametros!$H$10)),1,0) -> 1 | T89: =Q89+R89+S89 -> 4 | U89: =IF(OR(V89="Inactive",V89="No encontrada"),"Descartada",IF(AND(T89>=Parametros!$H$5,S89=1),"A",IF(T89>=Parametros!$H$6,"B","C"))) -> B | V89: Pendiente
A90: P086 | B90: Three Js Management Corporation | C90: Sunrise | E90: Broward | F90: Administración de propiedades | G90: 53 | H90: 53 Inmobiliario/admin. propiedades | I90: Corp | J90: No verificado | K90: No verificado | L90: No verificado | M90: Manta: est. 2001, ~5 empleados | N90: https://www.manta.com/c/mw2lslb/three-js-management-corporation | O90: 5 | Q90: =IFERROR(VLOOKUP(J90,Parametros!$A$5:$B$9,2,FALSE()),0) -> 1 | R90: =IFERROR(VLOOKUP(H90,Parametros!$D$5:$E$16,2,FALSE()),1) -> 2 | S90: =IF(OR(N(O90)>=Parametros!$H$9,AND(N(P90)>0,N(P90)<=Parametros!$H$10)),1,0) -> 0 | T90: =Q90+R90+S90 -> 3 | U90: =IF(OR(V90="Inactive",V90="No encontrada"),"Descartada",IF(AND(T90>=Parametros!$H$5,S90=1),"A",IF(T90>=Parametros!$H$6,"B","C"))) -> C | V90: Pendiente
A91: P087 | B91: Lindsay-Taylor Property Management Inc | C91: Sunrise | E91: Broward | F91: Administración de propiedades | G91: 53 | H91: 53 Inmobiliario/admin. propiedades | I91: Inc | J91: No verificado | K91: No verificado | L91: No verificado | M91: Manta: est. 2015, ~7 empleados | N91: https://www.manta.com/c/mhkhbr0/lindsay-taylor-property-management-inc | O91: 7 | Q91: =IFERROR(VLOOKUP(J91,Parametros!$A$5:$B$9,2,FALSE()),0) -> 1 | R91: =IFERROR(VLOOKUP(H91,Parametros!$D$5:$E$16,2,FALSE()),1) -> 2 | S91: =IF(OR(N(O91)>=Parametros!$H$9,AND(N(P91)>0,N(P91)<=Parametros!$H$10)),1,0) -> 0 | T91: =Q91+R91+S91 -> 3 | U91: =IF(OR(V91="Inactive",V91="No encontrada"),"Descartada",IF(AND(T91>=Parametros!$H$5,S91=1),"A",IF(T91>=Parametros!$H$6,"B","C"))) -> C | V91: Pendiente
A92: P088 | B92: YMP Real Estate Management LLC | C92: Sunrise | E92: Broward | F92: Administración de propiedades | G92: 53 | H92: 53 Inmobiliario/admin. propiedades | I92: LLC | J92: No verificado | K92: No verificado | L92: No verificado | M92: Manta: est. 2015, ~2 empleados | N92: https://www.manta.com/c/mbybsr5/ymp-real-estate-management-llc | O92: 2 | Q92: =IFERROR(VLOOKUP(J92,Parametros!$A$5:$B$9,2,FALSE()),0) -> 1 | R92: =IFERROR(VLOOKUP(H92,Parametros!$D$5:$E$16,2,FALSE()),1) -> 2 | S92: =IF(OR(N(O92)>=Parametros!$H$9,AND(N(P92)>0,N(P92)<=Parametros!$H$10)),1,0) -> 0 | T92: =Q92+R92+S92 -> 3 | U92: =IF(OR(V92="Inactive",V92="No encontrada"),"Descartada",IF(AND(T92>=Parametros!$H$5,S92=1),"A",IF(T92>=Parametros!$H$6,"B","C"))) -> C | V92: Pendiente
A93: P089 | B93: Kryterion Property Services LLC | C93: Sunrise | E93: Broward | F93: Administración de propiedades | G93: 53 | H93: 53 Inmobiliario/admin. propiedades | I93: LLC | J93: No verificado | K93: No verificado | L93: No verificado | M93: Listado Manta | N93: https://www.manta.com/c/mkxpthn/kryterion-property-services-llc | Q93: =IFERROR(VLOOKUP(J93,Parametros!$A$5:$B$9,2,FALSE()),0) -> 1 | R93: =IFERROR(VLOOKUP(H93,Parametros!$D$5:$E$16,2,FALSE()),1) -> 2 | S93: =IF(OR(N(O93)>=Parametros!$H$9,AND(N(P93)>0,N(P93)<=Parametros!$H$10)),1,0) -> 0 | T93: =Q93+R93+S93 -> 3 | U93: =IF(OR(V93="Inactive",V93="No encontrada"),"Descartada",IF(AND(T93>=Parametros!$H$5,S93=1),"A",IF(T93>=Parametros!$H$6,"B","C"))) -> C | V93: Pendiente
A94: P090 | B94: Lasseter Plumbing Company Inc | C94: North Miami | E94: Miami-Dade | F94: Plomería | G94: 23 | H94: 23 Construcción y oficios | I94: Inc | J94: No verificado | K94: No verificado | L94: No verificado | M94: Manta: ~$500k, ~7 empleados | N94: https://www.manta.com/d/mm2thx3/lasseter-plumbing-company-inc | O94: 7 | Q94: =IFERROR(VLOOKUP(J94,Parametros!$A$5:$B$9,2,FALSE()),0) -> 1 | R94: =IFERROR(VLOOKUP(H94,Parametros!$D$5:$E$16,2,FALSE()),1) -> 3 | S94: =IF(OR(N(O94)>=Parametros!$H$9,AND(N(P94)>0,N(P94)<=Parametros!$H$10)),1,0) -> 0 | T94: =Q94+R94+S94 -> 4 | U94: =IF(OR(V94="Inactive",V94="No encontrada"),"Descartada",IF(AND(T94>=Parametros!$H$5,S94=1),"A",IF(T94>=Parametros!$H$6,"B","C"))) -> B | V94: Pendiente
A95: P091 | B95: Rocco Plumbing Inc | C95: North Miami | E95: Miami-Dade | F95: Plomería | G95: 23 | H95: 23 Construcción y oficios | I95: Inc | J95: No verificado | K95: No verificado | L95: No verificado | M95: Manta: est. 2008 | N95: https://www.manta.com/c/mtbtgz9/rocco-plumbing-inc | Q95: =IFERROR(VLOOKUP(J95,Parametros!$A$5:$B$9,2,FALSE()),0) -> 1 | R95: =IFERROR(VLOOKUP(H95,Parametros!$D$5:$E$16,2,FALSE()),1) -> 3 | S95: =IF(OR(N(O95)>=Parametros!$H$9,AND(N(P95)>0,N(P95)<=Parametros!$H$10)),1,0) -> 0 | T95: =Q95+R95+S95 -> 4 | U95: =IF(OR(V95="Inactive",V95="No encontrada"),"Descartada",IF(AND(T95>=Parametros!$H$5,S95=1),"A",IF(T95>=Parametros!$H$6,"B","C"))) -> B | V95: Pendiente
A96: P092 | B96: Malu Plumbing Inc | C96: North Miami | E96: Miami-Dade | F96: Plomería | G96: 23 | H96: 23 Construcción y oficios | I96: Inc | J96: No verificado | K96: No verificado | L96: No verificado | M96: Manta: repiping, gas | N96: https://www.manta.com/c/mt4fd3r/malu-plumbing-inc | Q96: =IFERROR(VLOOKUP(J96,Parametros!$A$5:$B$9,2,FALSE()),0) -> 1 | R96: =IFERROR(VLOOKUP(H96,Parametros!$D$5:$E$16,2,FALSE()),1) -> 3 | S96: =IF(OR(N(O96)>=Parametros!$H$9,AND(N(P96)>0,N(P96)<=Parametros!$H$10)),1,0) -> 0 | T96: =Q96+R96+S96 -> 4 | U96: =IF(OR(V96="Inactive",V96="No encontrada"),"Descartada",IF(AND(T96>=Parametros!$H$5,S96=1),"A",IF(T96>=Parametros!$H$6,"B","C"))) -> B | V96: Pendiente
A97: P093 | B97: Just Plumbing | C97: North Miami | E97: Miami-Dade | F97: Plomería | G97: 23 | H97: 23 Construcción y oficios | I97: No verificado | J97: No verificado | K97: No verificado | L97: No verificado | M97: Listado Manta | N97: https://www.manta.com/c/mb04c42/just-plumbing | Q97: =IFERROR(VLOOKUP(J97,Parametros!$A$5:$B$9,2,FALSE()),0) -> 1 | R97: =IFERROR(VLOOKUP(H97,Parametros!$D$5:$E$16,2,FALSE()),1) -> 3 | S97: =IF(OR(N(O97)>=Parametros!$H$9,AND(N(P97)>0,N(P97)<=Parametros!$H$10)),1,0) -> 0 | T97: =Q97+R97+S97 -> 4 | U97: =IF(OR(V97="Inactive",V97="No encontrada"),"Descartada",IF(AND(T97>=Parametros!$H$5,S97=1),"A",IF(T97>=Parametros!$H$6,"B","C"))) -> B | V97: Pendiente
A98: P094 | B98: Plumbing Experts | C98: North Miami Beach | E98: Miami-Dade | F98: Plomería | G98: 23 | H98: 23 Construcción y oficios | I98: No verificado | J98: No verificado | K98: No verificado | L98: No verificado | M98: Listado Manta | N98: https://www.manta.com/c/mttg4zn/plumbing-experts | Q98: =IFERROR(VLOOKUP(J98,Parametros!$A$5:$B$9,2,FALSE()),0) -> 1 | R98: =IFERROR(VLOOKUP(H98,Parametros!$D$5:$E$16,2,FALSE()),1) -> 3 | S98: =IF(OR(N(O98)>=Parametros!$H$9,AND(N(P98)>0,N(P98)<=Parametros!$H$10)),1,0) -> 0 | T98: =Q98+R98+S98 -> 4 | U98: =IF(OR(V98="Inactive",V98="No encontrada"),"Descartada",IF(AND(T98>=Parametros!$H$5,S98=1),"A",IF(T98>=Parametros!$H$6,"B","C"))) -> B | V98: Pendiente
A99: P095 | B99: New England Plumbing | C99: Miami Shores | E99: Miami-Dade | F99: Plomería | G99: 23 | H99: 23 Construcción y oficios | I99: No verificado | J99: No verificado | K99: No verificado | L99: No verificado | M99: Listado Manta | N99: https://www.manta.com/c/mx0vyzw/new-england-plumbing | Q99: =IFERROR(VLOOKUP(J99,Parametros!$A$5:$B$9,2,FALSE()),0) -> 1 | R99: =IFERROR(VLOOKUP(H99,Parametros!$D$5:$E$16,2,FALSE()),1) -> 3 | S99: =IF(OR(N(O99)>=Parametros!$H$9,AND(N(P99)>0,N(P99)<=Parametros!$H$10)),1,0) -> 0 | T99: =Q99+R99+S99 -> 4 | U99: =IF(OR(V99="Inactive",V99="No encontrada"),"Descartada",IF(AND(T99>=Parametros!$H$5,S99=1),"A",IF(T99>=Parametros!$H$6,"B","C"))) -> B | V99: Pendiente

Sheet TD_Area_Web
A1: Tabla dinámica: prospectos por condado, municipio y estado web
A2: Origen: hoja Prospectos. Clic derecho > Actualizar tras editar datos. Filtros en la fila superior de la tabla.
A4: Filter
A6: Count - Empresa | C6: Estado web
A7: Condado | B7: Municipio | C7: No verificado | D7: Presencia desordenada | E7: Sin sitio web | F7: Sitio obsoleto | G7: Tiene web (auditar) | H7: Total Result
A8: Broward | B8: Davie | C8: 2 | D8: 1 | E8: 2 | H8: 5
B9: Fort Lauderdale | C9: 1 | E9: 5 | F9: 1 | H9: 7
B10: Miramar | C10: 4 | H10: 4
B11: Pompano Beach | C11: 7 | E11: 2 | F11: 1 | H11: 10
B12: Sunrise | C12: 5 | H12: 5
A13: Miami-Dade | B13: Doral | C13: 5 | G13: 3 | H13: 8
B14: Hialeah | C14: 6 | D14: 1 | E14: 3 | F14: 1 | G14: 3 | H14: 14
B15: Hialeah Gardens | F15: 1 | H15: 1
B16: Homestead | C16: 5 | E16: 1 | G16: 2 | H16: 8
B17: Kendall | C17: 2 | G17: 1 | H17: 3
B18: Medley | C18: 4 | D18: 1 | E18: 2 | F18: 4 | G18: 6 | H18: 17
B19: Miami (ciudad) | C19: 2 | G19: 4 | H19: 6
B20: Miami Beach | C20: 1 | H20: 1
B21: Miami Shores | C21: 1 | H21: 1
B22: North Miami | C22: 4 | H22: 4
B23: North Miami Beach | C23: 1 | H23: 1
A24: Total Result | C24: 50 | D24: 3 | E24: 15 | F24: 8 | G24: 19 | H24: 95

Sheet TD_Industria_Web
A1: Tabla dinámica: industria × estado web (filtro: condado)
A2: Origen: hoja Prospectos. Clic derecho > Actualizar tras editar datos. Filtros en la fila superior de la tabla.
A4: Filter
A5: Condado | B5: - all -
A7: Count - Empresa | B7: Estado web
A8: Industria (NAICS) | B8: No verificado | C8: Presencia desordenada | D8: Sin sitio web | E8: Sitio obsoleto | F8: Tiene web (auditar) | G8: Total Result
A9: 11 Agricultura/viveros | B9: 5 | F9: 1 | G9: 6
A10: 23 Construcción y oficios | B10: 11 | D10: 3 | E10: 2 | F10: 1 | G10: 17
A11: 31-33 Manufactura | B11: 3 | D11: 3 | E11: 1 | F11: 4 | G11: 11
A12: 42 Comercio mayorista | B12: 4 | D12: 1 | E12: 1 | F12: 7 | G12: 13
A13: 48-49 Transporte y logística | B13: 7 | D13: 1 | E13: 2 | F13: 3 | G13: 13
A14: 53 Inmobiliario/admin. propiedades | B14: 5 | G14: 5
A15: 62 Salud | B15: 4 | G15: 4
A16: 72 Restaurantes/hotelería | B16: 1 | F16: 1 | G16: 2
A17: 81 Servicios (auto, náutico, reparación) | B17: 10 | C17: 3 | D17: 7 | E17: 2 | F17: 2 | G17: 24
A18: Total Result | B18: 50 | C18: 3 | D18: 15 | E18: 8 | F18: 19 | G18: 95

Sheet TD_Legal_Prioridad
A1: Tabla dinámica: forma legal × prioridad (filtro: condado)
A2: Origen: hoja Prospectos. Clic derecho > Actualizar tras editar datos. Filtros en la fila superior de la tabla.
A4: Filter
A5: Condado | B5: - all -
A7: Count - Empresa | B7: Prioridad
A8: Forma legal | B8: A | C8: B | D8: C | E8: Descartada | F8: Total Result
A9: Corp | B9: 3 | C9: 2 | D9: 2 | F9: 7
A10: Inc | B10: 6 | C10: 31 | D10: 9 | E10: 1 | F10: 47
A11: LLC | B11: 1 | C11: 7 | D11: 4 | F11: 12
A12: No verificado | B12: 3 | C12: 10 | D12: 16 | F12: 29
A13: Total Result | B13: 13 | C13: 50 | D13: 31 | E13: 1 | F13: 95

Sheet TD_Redes
A1: Tabla dinámica: presencia en redes sociales × condado (filtro: industria)
A2: Origen: hoja Prospectos. Clic derecho > Actualizar tras editar datos. Filtros en la fila superior de la tabla.
A4: Filter
A5: Industria (NAICS) | B5: - all -
A7: Count - Empresa | B7: Condado
A8: Tiene redes | B8: Broward | C8: Miami-Dade | D8: Total Result
A9: No | B9: 6 | C9: 29 | D9: 35
A10: No verificado | B10: 19 | C10: 6 | D10: 25
A11: Sí | B11: 6 | C11: 29 | D11: 35
A12: Total Result | B12: 31 | C12: 64 | D12: 95

Sheet Parametros
A1: Parámetros del puntaje
A2: Azul = supuestos editables. El puntaje de Prospectos se recalcula al cambiarlos.
A4: Estado web | B4: Peso | D4: Industria (NAICS) | E4: Peso | G4: Prioridad | H4: Puntaje mínimo
A5: Sin sitio web | B5: 3 | D5: 23 Construcción y oficios | E5: 3 | G5: A | H5: 6 | I5: CPL $76–228: alto valor por cliente
A6: Sitio obsoleto | B6: 3 | D6: 48-49 Transporte y logística | E6: 3 | G6: B | H6: 4 | I6: B2B, tamaño medio, baja madurez digital
A7: Presencia desordenada | B7: 2 | D7: 62 Salud | E7: 3 | G7: C | H7: < B | I7: CPC $5–10, alta intención local
A8: No verificado | B8: 1 | D8: 54 Servicios profesionales | E8: 3 | I8: CPC legal $9.87+, ticket alto
A9: Tiene web (auditar) | B9: 1 | D9: 42 Comercio mayorista | E9: 2 | G9: Empleados mín. | H9: 10 | I9: B2B CPL $103; decisión lenta
D10: 31-33 Manufactura | E10: 2 | G10: Fundada hasta | H10: 2000 | I10: B2B, catálogo/cotizador
D11: 53 Inmobiliario/admin. propiedades | E11: 2 | I11: CPL $100
D12: 81 Servicios (auto, náutico, reparación) | E12: 2 | I12: Náutico FTL: ticket alto; auto CPL $28
D13: 72 Restaurantes/hotelería | E13: 1 | I13: Ticket bajo, CPC $2
D14: 11 Agricultura/viveros | E14: 1 | I14: Mayorista, baja demanda de search
D15: Sin clasificar | E15: 1
A18: Puntaje = Peso web + Peso sector + Señal tamaño (1 si ≥10 empleados/camiones o fundada ≤2000). Máx. 7. Prioridad A exige además Señal tamaño = 1 (empresa mediana/establecida). Inactive en Sunbiz = Descartada.
A19: Pesos de sector derivados de benchmarks Google Ads (hoja Google_Ads) y ticket de servicio esperado. Criterio propio, ajustable.

Sheet Oportunidad_Industria
A1: Matriz de oportunidad por industria
A2: Conteos vivos desde Prospectos. Ticket y CPL = supuestos editables (azul) con fuente en Google_Ads.
A4: Industria (NAICS) | B4: Prospectos | C4: Sin web | D4: Sitio obsoleto | E4: Desordenada | F4: Brecha (sin web+obsoleto+desordenada) | G4: % brecha | H4: Prioridad A | I4: Ticket web (USD) | J4: Retainer mensual (USD) | K4: Valor potencial año 1 (USD) | L4: CPL ref. Google Ads (USD)
A5: 23 Construcción y oficios | B5: =COUNTIF(Prospectos!$H$5:$H$99,A5) -> 17 | C5: =COUNTIFS(Prospectos!$H$5:$H$99,A5,Prospectos!$J$5:$J$99,"Sin sitio web") -> 3 | D5: =COUNTIFS(Prospectos!$H$5:$H$99,A5,Prospectos!$J$5:$J$99,"Sitio obsoleto") -> 2 | E5: =COUNTIFS(Prospectos!$H$5:$H$99,A5,Prospectos!$J$5:$J$99,"Presencia desordenada") -> 0 | F5: =C5+D5+E5 -> 5 | G5: =IF(B5=0,0,F5/B5) -> 0.29411765 | H5: =COUNTIFS(Prospectos!$H$5:$H$99,A5,Prospectos!$U$5:$U$99,"A") -> 3 | I5: 4500 | J5: 1500 | K5: =F5*(I5+J5*12) -> 112500 | L5: 76.4
A6: 48-49 Transporte y logística | B6: =COUNTIF(Prospectos!$H$5:$H$99,A6) -> 13 | C6: =COUNTIFS(Prospectos!$H$5:$H$99,A6,Prospectos!$J$5:$J$99,"Sin sitio web") -> 1 | D6: =COUNTIFS(Prospectos!$H$5:$H$99,A6,Prospectos!$J$5:$J$99,"Sitio obsoleto") -> 2 | E6: =COUNTIFS(Prospectos!$H$5:$H$99,A6,Prospectos!$J$5:$J$99,"Presencia desordenada") -> 0 | F6: =C6+D6+E6 -> 3 | G6: =IF(B6=0,0,F6/B6) -> 0.23076923 | H6: =COUNTIFS(Prospectos!$H$5:$H$99,A6,Prospectos!$U$5:$U$99,"A") -> 3 | I6: 5000 | J6: 1500 | K6: =F6*(I6+J6*12) -> 69000 | L6: 103.54
A7: 62 Salud | B7: =COUNTIF(Prospectos!$H$5:$H$99,A7) -> 4 | C7: =COUNTIFS(Prospectos!$H$5:$H$99,A7,Prospectos!$J$5:$J$99,"Sin sitio web") -> 0 | D7: =COUNTIFS(Prospectos!$H$5:$H$99,A7,Prospectos!$J$5:$J$99,"Sitio obsoleto") -> 0 | E7: =COUNTIFS(Prospectos!$H$5:$H$99,A7,Prospectos!$J$5:$J$99,"Presencia desordenada") -> 0 | F7: =C7+D7+E7 -> 0 | G7: =IF(B7=0,0,F7/B7) -> 0 | H7: =COUNTIFS(Prospectos!$H$5:$H$99,A7,Prospectos!$U$5:$U$99,"A") -> 0 | I7: 4500 | J7: 1800 | K7: =F7*(I7+J7*12) -> 0 | L7: 56.83
A8: 54 Servicios profesionales | B8: =COUNTIF(Prospectos!$H$5:$H$99,A8) -> 0 | C8: =COUNTIFS(Prospectos!$H$5:$H$99,A8,Prospectos!$J$5:$J$99,"Sin sitio web") -> 0 | D8: =COUNTIFS(Prospectos!$H$5:$H$99,A8,Prospectos!$J$5:$J$99,"Sitio obsoleto") -> 0 | E8: =COUNTIFS(Prospectos!$H$5:$H$99,A8,Prospectos!$J$5:$J$99,"Presencia desordenada") -> 0 | F8: =C8+D8+E8 -> 0 | G8: =IF(B8=0,0,F8/B8) -> 0 | H8: =COUNTIFS(Prospectos!$H$5:$H$99,A8,Prospectos!$U$5:$U$99,"A") -> 0 | I8: 6000 | J8: 2000 | K8: =F8*(I8+J8*12) -> 0 | L8: 131.63
A9: 42 Comercio mayorista | B9: =COUNTIF(Prospectos!$H$5:$H$99,A9) -> 13 | C9: =COUNTIFS(Prospectos!$H$5:$H$99,A9,Prospectos!$J$5:$J$99,"Sin sitio web") -> 1 | D9: =COUNTIFS(Prospectos!$H$5:$H$99,A9,Prospectos!$J$5:$J$99,"Sitio obsoleto") -> 1 | E9: =COUNTIFS(Prospectos!$H$5:$H$99,A9,Prospectos!$J$5:$J$99,"Presencia desordenada") -> 0 | F9: =C9+D9+E9 -> 2 | G9: =IF(B9=0,0,F9/B9) -> 0.15384615 | H9: =COUNTIFS(Prospectos!$H$5:$H$99,A9,Prospectos!$U$5:$U$99,"A") -> 1 | I9: 4000 | J9: 1200 | K9: =F9*(I9+J9*12) -> 36800 | L9: 103.54
A10: 31-33 Manufactura | B10: =COUNTIF(Prospectos!$H$5:$H$99,A10) -> 11 | C10: =COUNTIFS(Prospectos!$H$5:$H$99,A10,Prospectos!$J$5:$J$99,"Sin sitio web") -> 3 | D10: =COUNTIFS(Prospectos!$H$5:$H$99,A10,Prospectos!$J$5:$J$99,"Sitio obsoleto") -> 1 | E10: =COUNTIFS(Prospectos!$H$5:$H$99,A10,Prospectos!$J$5:$J$99,"Presencia desordenada") -> 0 | F10: =C10+D10+E10 -> 4 | G10: =IF(B10=0,0,F10/B10) -> 0.36363636 | H10: =COUNTIFS(Prospectos!$H$5:$H$99,A10,Prospectos!$U$5:$U$99,"A") -> 2 | I10: 4000 | J10: 1200 | K10: =F10*(I10+J10*12) -> 73600 | L10: 103.54
A11: 53 Inmobiliario/admin. propiedades | B11: =COUNTIF(Prospectos!$H$5:$H$99,A11) -> 5 | C11: =COUNTIFS(Prospectos!$H$5:$H$99,A11,Prospectos!$J$5:$J$99,"Sin sitio web") -> 0 | D11: =COUNTIFS(Prospectos!$H$5:$H$99,A11,Prospectos!$J$5:$J$99,"Sitio obsoleto") -> 0 | E11: =COUNTIFS(Prospectos!$H$5:$H$99,A11,Prospectos!$J$5:$J$99,"Presencia desordenada") -> 0 | F11: =C11+D11+E11 -> 0 | G11: =IF(B11=0,0,F11/B11) -> 0 | H11: =COUNTIFS(Prospectos!$H$5:$H$99,A11,Prospectos!$U$5:$U$99,"A") -> 0 | I11: 3500 | J11: 1200 | K11: =F11*(I11+J11*12) -> 0 | L11: 100.48
A12: 81 Servicios (auto, náutico, reparación) | B12: =COUNTIF(Prospectos!$H$5:$H$99,A12) -> 24 | C12: =COUNTIFS(Prospectos!$H$5:$H$99,A12,Prospectos!$J$5:$J$99,"Sin sitio web") -> 7 | D12: =COUNTIFS(Prospectos!$H$5:$H$99,A12,Prospectos!$J$5:$J$99,"Sitio obsoleto") -> 2 | E12: =COUNTIFS(Prospectos!$H$5:$H$99,A12,Prospectos!$J$5:$J$99,"Presencia desordenada") -> 3 | F12: =C12+D12+E12 -> 12 | G12: =IF(B12=0,0,F12/B12) -> 0.5 | H12: =COUNTIFS(Prospectos!$H$5:$H$99,A12,Prospectos!$U$5:$U$99,"A") -> 4 | I12: 3000 | J12: 1000 | K12: =F12*(I12+J12*12) -> 180000 | L12: 28.5
A13: 72 Restaurantes/hotelería | B13: =COUNTIF(Prospectos!$H$5:$H$99,A13) -> 2 | C13: =COUNTIFS(Prospectos!$H$5:$H$99,A13,Prospectos!$J$5:$J$99,"Sin sitio web") -> 0 | D13: =COUNTIFS(Prospectos!$H$5:$H$99,A13,Prospectos!$J$5:$J$99,"Sitio obsoleto") -> 0 | E13: =COUNTIFS(Prospectos!$H$5:$H$99,A13,Prospectos!$J$5:$J$99,"Presencia desordenada") -> 0 | F13: =C13+D13+E13 -> 0 | G13: =IF(B13=0,0,F13/B13) -> 0 | H13: =COUNTIFS(Prospectos!$H$5:$H$99,A13,Prospectos!$U$5:$U$99,"A") -> 0 | I13: 2500 | J13: 800 | K13: =F13*(I13+J13*12) -> 0 | L13: 30.27
A14: 11 Agricultura/viveros | B14: =COUNTIF(Prospectos!$H$5:$H$99,A14) -> 6 | C14: =COUNTIFS(Prospectos!$H$5:$H$99,A14,Prospectos!$J$5:$J$99,"Sin sitio web") -> 0 | D14: =COUNTIFS(Prospectos!$H$5:$H$99,A14,Prospectos!$J$5:$J$99,"Sitio obsoleto") -> 0 | E14: =COUNTIFS(Prospectos!$H$5:$H$99,A14,Prospectos!$J$5:$J$99,"Presencia desordenada") -> 0 | F14: =C14+D14+E14 -> 0 | G14: =IF(B14=0,0,F14/B14) -> 0 | H14: =COUNTIFS(Prospectos!$H$5:$H$99,A14,Prospectos!$U$5:$U$99,"A") -> 0 | I14: 3000 | J14: 800 | K14: =F14*(I14+J14*12) -> 0 | L14: 70.11
A15: Total | B15: =SUM(B5:B14) -> 95 | C15: =SUM(C5:C14) -> 15 | D15: =SUM(D5:D14) -> 8 | E15: =SUM(E5:E14) -> 3 | F15: =SUM(F5:F14) -> 26 | G15: =IF(B15=0,0,F15/B15) -> 0.27368421 | H15: =SUM(H5:H14) -> 13 | K15: =SUM(K5:K14) -> 471900
A17: Valor potencial año 1 = empresas con brecha × (ticket web + retainer × 12). Asume 100% de cierre: aplicar tasa de conversión real (típico B2B frío 2–5%).
A18: Tickets: rangos Miami web pyme $2,500–15,000; SEO local $750–3,000/mes; redes $1,000–3,000/mes (ver Google_Ads). Valores de la tabla = punto medio conservador.

Sheet Macro_Areas
A1: Contexto económico por área
A2: Census QuickFacts / ABS 2022, municipios y DataUSA. 'Estimado' = no verificado en fuente primaria.
A4: Área | B4: Condado | C4: Población | D4: Año | E4: Firmas empleadoras (ABS 2022) | F4: Carácter económico | G4: NAICS clave | H4: Verificación | I4: Fuente
A5: Miami (ciudad) | B5: Miami-Dade | C5: 455924 | D5: 2023 | E5: 17986 | F5: Finanzas, servicios profesionales, turismo, hub LatAm | G5: 54, 52, 72, 42 | H5: Sí | I5: https://www.census.gov/quickfacts/fact/table/miamicityflorida/PST045224
A6: Hialeah | B6: Miami-Dade | C6: 226000 | D6: 2024 | F6: Manufactura ligera, salud, construcción, transporte | G6: 31-33, 62, 23, 48-49 | H6: Estimado | I6: https://datausa.io/profile/geo/hialeah-fl/
A7: Doral | B7: Miami-Dade | C7: 83625 | D7: 2024 | E7: 5300 | F7: Logística, comercio exterior, freight forwarders (junto a MIA) | G7: 48-49, 42, 54, 44-45 | H7: Estimado | I7: https://www.census.gov/quickfacts/fact/table/doralcityflorida/PST045225
A8: Medley | B8: Miami-Dade | C8: 1056 | D8: 2020 | E8: 1800 | F8: Industrial pura: cemento, canteras, +350 almacenes; población diurna +60k | G8: 31-33, 42, 48-49, 23 | H8: Sí (municipio) | I8: https://www.townofmedley.com/about-us
A9: Miami Beach | B9: Miami-Dade | C9: 82031 | D9: 2024 | E9: 4174 | F9: Hotelería, restaurantes, vida nocturna, real estate | G9: 72, 53, 71, 81 | H9: Sí | I9: https://census.gov/quickfacts/fact/table/miamibeachcityflorida/POP060210
A10: Coral Gables | B10: Miami-Dade | C10: 48353 | D10: 2023 | E10: 5120 | F10: Sedes multinacionales LatAm, legal, profesional | G10: 54, 52, 55, 62 | H10: Sí | I10: https://www.census.gov/quickfacts/fact/table/coralgablescityflorida/PST045224
A11: Kendall | B11: Miami-Dade | C11: 80241 | D11: 2020 | F11: Retail (Dadeland), salud (Baptist), servicios | G11: 44-45, 62, 81, 61 | H11: Sí (población) | I11: https://en.wikipedia.org/wiki/Kendall,_Florida
A12: Miami Gardens | B12: Miami-Dade | C12: 111000 | D12: 2024 | F12: Residencial, retail, Hard Rock Stadium | G12: 44-45, 71, 81 | H12: Estimado | I12: https://www.census.gov/quickfacts/fact/table/miamigardenscityflorida/POP060210
A13: Homestead | B13: Miami-Dade | C13: 82807 | D13: 2024 | E13: 1212 | F13: Agricultura/viveros, base aérea, puerta a Cayos | G13: 11, 44-45, 72, 23 | H13: Sí | I13: https://census.gov/quickfacts/fact/table/homesteadcityflorida/PST120223
A14: Fort Lauderdale | B14: Broward | C14: 184255 | D14: 2023 | E14: 10690 | F14: Industria náutica (111k empleos Broward), turismo, finanzas | G14: 48-49, 72, 52, 81 | H14: Sí | I14: https://www.census.gov/quickfacts/fact/table/fortlauderdalecityflorida/PST045225
A15: Hollywood | B15: Broward | C15: 152650 | D15: 2022 | E15: 5007 | F15: Turismo de playa, retail, servicios | G15: 72, 44-45, 81 | H15: Sí | I15: https://www.census.gov/quickfacts/fact/table/hollywoodcityflorida/PST045222
A16: Pembroke Pines | B16: Broward | C16: 179326 | D16: 2024 | E16: 4128 | F16: Residencial, retail, salud | G16: 44-45, 62, 81 | H16: Sí | I16: https://www.census.gov/quickfacts/fact/table/pembrokepinescityflorida/SBO010222
A17: Sunrise | B17: Broward | C17: 100128 | D17: 2024 | E17: 2706 | F17: Retail (Sawgrass Mills), oficinas corporativas | G17: 44-45, 55, 54 | H17: Sí | I17: https://www.census.gov/quickfacts/fact/table/sunrisecityflorida/PST045222
A18: Plantation | B18: Broward | C18: 96000 | D18: 2024 | F18: Oficinas, salud, retail | G18: 54, 62, 44-45 | H18: Estimado | I18: https://www.census.gov/quickfacts/fact/table/plantationcityflorida/PST045225
A20: Condados
A21: Condado | B21: Población | C21: Establecimientos (CBP) | D21: Año | E21: Est. 20–99 empl. | F21: Est. 100–499 empl. | G21: Mid-market (20–499) | H21: % mid-market | I21: Fuente
A22: Miami-Dade | B22: 2738356 | C22: 98394 | D22: 2023 | E22: 12000 | F22: 2200 | G22: =E22+F22 -> 14200 | H22: =IF(C22=0,0,G22/C22) -> 0.14431774 | I22: https://www.miamidadematters.org/indicators/index/view?indicatorId=6371&localeId=414
A23: Broward | B23: 2000000 | C23: 67274 | D23: 2022 | E23: 8200 | F23: 1500 | G23: =E23+F23 -> 9700 | H23: =IF(C23=0,0,G23/C23) -> 0.14418646 | I23: https://www.census.gov/quickfacts/fact/table/browardcountyflorida/PST045224
A24: Est. 20–99 y 100–499 = ESTIMADO (proporciones nacionales CBP ≈12% y ≈2.2%). Verificar en data.census.gov tabla CB2300CBP, FIPS 12086 y 12011.

Sheet Adopcion_Digital
A1: Adopción digital y formación de empresas
A2: Encuestas nacionales (no hay datos específicos de Florida) + estadísticas oficiales.
A4: Indicador | B4: Valor | C4: Año | D4: Fuente | E4: URL
A5: Pequeñas empresas EE.UU. sin sitio web | B5: 17% | C5: 2025 | D5: Clutch | E5: https://clutch.co/press-releases/smb-websites-2025
A6: Sin sitio web (Top Design Firms) | B6: 27% | C6: 2022 | D6: Top Design Firms | E6: https://www.prnewswire.com/news-releases/27-of-small-businesses-still-dont-have-a-website-in-2022-301542302.html
A7: De las que no tienen web: creen que no la necesitan | B7: 34% | C7: 2025 | D7: Clutch | E7: https://clutch.co/press-releases/smb-websites-2025
A8: Invierten en publicidad de búsqueda (año en curso) | B8: 45% | C8: 2026 | D8: LocaliQ | E8: https://localiq.com/blog/small-business-marketing-trends-report-2026/
A9: Invierten en search con presupuesto < $1k/mes | B9: 30% | C9: 2026 | D9: LocaliQ | E9: https://localiq.com/blog/small-business-marketing-trends-report-2026/
A10: Pymes que usan IA generativa | B10: 58% | C10: 2025 | D10: US Chamber | E10: https://www.uschamber.com/technology/artificial-intelligence/u-s-chambers-latest-empowering-small-business-report-shows-majority-of-businesses-in-all-50-states-are-embracing-ai
A11: Solicitudes de negocio Florida (Census BFS) | B11: ~634,000 | C11: 2024 | D11: Census BFS / Business Observer | E11: https://www.businessobserverfl.com/news/2025/may/19/florida-new-business-formations/
A12: Solicitudes por 10k hab. Miami-Dade (6.º EE.UU.) | B12: 532 | C12: 2024 | D12: Census BFS / Business Observer | E12: https://www.businessobserverfl.com/news/2025/may/19/florida-new-business-formations/
A13: Solicitudes por 10k hab. Broward (11.º EE.UU.) | B13: 418 | C13: 2024 | D13: Census BFS / Business Observer | E13: https://www.businessobserverfl.com/news/2025/may/19/florida-new-business-formations/
A14: Pequeñas empresas en Florida (99.8% del total) | B14: 3.5 M | C14: 2025 | D14: SBA Office of Advocacy | E14: https://advocacy.sba.gov/wp-content/uploads/2025/06/Florida_2025-State-Profile.pdf
A15: Entidades registradas en Sunbiz | B15: +3.5 M | C15: 2026 | D15: Florida Division of Corporations | E15: https://dos.fl.gov/sunbiz/
... A18: Demandas digitales ADA Florida (fed.+estatal) | B18: 950 (24% EE.UU.) | C18: 2025 | D18: UsableNet | E18: https://blog.usablenet.com/ada-web-lawsuit-trends-2026

Sheet Google_Ads
A1: Google Ads: benchmarks y precios de servicios
A2: WordStream/LocaliQ = muestras grandes. Keywords Miami = herramientas de agencia (orientativo). Confirmar con Keyword Planner.
A4: Industria / keyword | B4: NAICS | C4: CPC (USD) | D4: CPL (USD) | E4: Nota | F4: Fuente
A5: Promedio todas las industrias | C5: 5.26 | D5: 70.11 | E5: WordStream 2025 (16k+ campañas) | F5: https://www.wordstream.com/blog/2025-google-ads-benchmarks
A6: Legal / abogados | B6: 54 | C6: 9.87 | D6: 131.63 | E6: CPC 2026; CPL más alto | F6: https://www.wordstream.com/blog/2026-google-ads-benchmarks
A7: Dental | B7: 62 | C7: 8 | E7: CPC 2026; conv. 9.08% | F7: https://www.wordstream.com/blog/2026-google-ads-benchmarks
A8: Médicos y cirujanos | B8: 62 | C8: 5 | D8: 56.83 | E8: WordStream 2025 | F8: https://www.wordstream.com/blog/2025-google-ads-benchmarks
A9: Techos (roofing) | B9: 23 | C9: 10.7 | D9: 228.15 | E9: LocaliQ home services 2025 | F9: https://localiq.com/blog/home-services-search-advertising-benchmarks/
A10: Plomería | B10: 23 | D10: 76.4 | E10: LocaliQ home services 2025 | F10: https://localiq.com/blog/home-services-search-advertising-benchmarks/
A11: HVAC | B11: 23 | D11: 84.92 | E11: LocaliQ home services 2025 | F11: https://localiq.com/blog/home-services-search-advertising-benchmarks/
A12: Construcción | B12: 23 | C12: 5.31 | E12: LocaliQ home services 2025 | F12: https://localiq.com/blog/home-services-search-advertising-benchmarks/
A13: Automotriz (reparación) | B13: 81 | D13: 28.5 | E13: WordStream 2025 | F13: https://www.wordstream.com/blog/2025-google-ads-benchmarks
A14: Restaurantes | B14: 72 | C14: 2.05 | D14: 30.27 | E14: WordStream 2025 | F14: https://www.wordstream.com/blog/2025-google-ads-benchmarks
A15: Business services (B2B) | B15: 42 | D15: 103.54 | E15: WordStream 2025 | F15: https://www.wordstream.com/blog/2025-google-ads-benchmarks
A16: Real estate | B16: 53 | D16: 100.48 | E16: WordStream 2025 | F16: https://www.wordstream.com/blog/2025-google-ads-benchmarks
A17: 'dentist miami' | B17: 62 | C17: 9.81 | D17: 105 | E17: Herramienta de agencia; orientativo | F17: https://ppcchief.com/google-ads-cost/dental/miami
A18: Accidentes / PI Miami (inglés) | B18: 54 | C18: 70 | D18: 300 | E18: Rango CPC $70–250+; CPL $300–1,000 | F18: https://custom.legal/practice-areas/personal-injury-law-firm-marketing/cost-per-click-benchmarks-for-personal-injury/
A19: 'abogado de accidentes' FL (español) | B19: 54 | C19: 45 | E19: CPC $45–85; 30–60% más barato que inglés | F19: https://www.greatmarketing.ai/blog/spanish-speaking-personal-injury-lawyer-marketing
A21: Precios de mercado de servicios digitales (Miami)
A22: Servicio | B22: Mínimo (USD) | C22: Máximo (USD) | D22: Punto medio | E22: Unidad | F22: Fuente
A23: Diseño web pyme (Miami) | B23: 2500 | C23: 15000 | D23: =AVERAGE(B23:C23) -> 8750 | E23: proyecto | F23: https://tamer.marketing/blog/web-design-cost-miami/
A24: Diseño web freelance / precio fijo | B24: 500 | C24: 2000 | D24: =AVERAGE(B24:C24) -> 1250 | E24: proyecto | F24: https://startupstarz.com/how-much-does-a-website-cost-for-a-small-business-in-miami-2026-pricing-guide/
A25: SEO local pyme (Miami) | B25: 750 | C25: 3000 | D25: =AVERAGE(B25:C25) -> 1875 | E25: mes | F25: https://tamer.marketing/blog/seo-cost-miami/
A26: Gestión redes sociales pyme (Miami) | B26: 1000 | C26: 3000 | D26: =AVERAGE(B26:C26) -> 2000 | E26: mes | F26: https://onceonceagency.com/social-media-management-cost-miami/
A27: Gestión Google Ads (fee) | B27: 500 | C27: 2500 | D27: =AVERAGE(B27:C27) -> 1500 | E27: mes (10–20% del gasto, mín. ~$500) | F27: https://www.2pointagency.com/glossary/pricing-for-ppc-management-services-in-miami/
A28: Presupuesto Google Ads pyme local | B28: 1000 | C28: 2500 | D28: =AVERAGE(B28:C28) -> 1750 | E28: mes (inversión del cliente) | F28: https://www.americaneagle.com/insights/blog/post/how-much-does-it-cost-to-advertise-on-google-ads-in-2025

Sheet Legal_Cumplimiento
A1: Legalidad de empresas y cumplimiento comercial
A2: Florida Division of Corporations (Sunbiz), DBPR, BTR condado/ciudad, FTSA, TCPA, CAN-SPAM, ADA. No es asesoría legal.
A4: Tema | B4: Regla / dato | C4: Implicación comercial | D4: Fuente oficial
A5: Sunbiz – tipos de entidad | B5: Florida Profit Corp, Not For Profit, LLC, LP/LLLP, Foreign, Fictitious Name (DBA, $50, 5 años, F.S. 865.09) | C5: 'Inc/Corp/LLC' en el nombre no confirma estatus: validar siempre en Sunbiz | D5: https://dos.fl.gov/sunbiz/start-business/efile/fl-fictitious-name-registration/
A6: Sunbiz – estados | B6: Active / Inactive (Admin Dissolution for Annual Report, Voluntary Dissolution, Revoked, Merged) | C6: Solo prospectar entidades Active; Inactive recientes = empresas desorganizadas (posible servicio) | D6: https://search.sunbiz.org/
A7: Sunbiz – Annual Report | B7: Vence 1 de mayo; LLC $138.75; recargo $400 (Corp/LLC/LP), no condonable | C7: Pico de disoluciones administrativas en la 4.ª semana de septiembre | D7: https://dos.fl.gov/sunbiz/manage-business/efile/annual-report/
A8: Sunbiz – datos públicos | B8: Document No., FEI/EIN, fecha, estado, dirección, registered agent, officers, historial | C8: Nombre del officer = decisor para contacto B2B | D8: https://dos.fl.gov/sunbiz/search/
A9: Sunbiz – descargas masivas | B9: SFTP sftp.floridados.gov: trimestral (todas las activas) y diario (nuevas altas), ancho fijo | C9: Fuente para lead-gen automatizado de empresas nuevas (siguiente fase) | D9: https://dos.fl.gov/sunbiz/other-services/data-downloads/
A10: DBPR – licencias | B10: Contratistas (CILB), hoteles y restaurantes, real estate, cosmetología, CPA, etc. 1.6M+ licenciatarios | C10: Cruzar licencia activa = negocio operativo y regulado | D10: https://www2.myfloridalicense.com/services-requiring-a-dbpr-license/
A11: BTR Miami-Dade | B11: Por local y clasificación; ciudad + condado; año fiscal 1 oct–30 sep | C11: Dataset abierto 'Local Business Tax – View' para prospección por dirección | D11: https://www.mdctaxcollector.gov/services/local-business-tax-receipt
A12: BTR Broward | B12: Obligatorio; renovación 1 jul–30 sep; tarifa por tipo y empleados | C12: Dataset 'Business Tax Records' en Broward GeoHub | D12: https://browardtax.org/business-tax-receipt/
A13: BTR/CU Fort Lauderdale | B13: BTR municipal obligatorio antes de operar (Sec. 15-28) | C13: Validar negocio operativo | D13: https://www.fortlauderdale.gov/Government/Departments/Community-Services/Business-Tax
A14: BTR/CU Miami Beach | B14: Certificate of Use + inspección bomberos + BTR | C14: Validar negocio operativo | D14: https://www.miamibeachfl.gov/city-hall/finance/business-tax-receipts-btr/
A15: BTR/CU Medley | B15: Sin CU no hay BTR; CU municipal exige CU del condado | C15: Validar negocio operativo | D15: https://www.townofmedley.com/local-business-tax-receipts
... A21: ADA web (Title III) | B21: Florida: 1,823 demandas ADA Title III en 2025 (2.º de EE.UU.); ~950 digitales (24%) | C21: Argumento de venta: sitio accesible (WCAG 2.2 AA) reduce riesgo legal | D21: https://www.adatitleiii.com/2026/02/ada-title-iii-federal-lawsuit-filings-fall-slightly-to-8667-in-2025/
A23: Portales de datos abiertos para escalar la base de prospectos
A24: Miami-Dade Open Data – Local Business Tax View | D24: https://opendata.miamidade.gov/datasets/local-business-tax-view
A25: Miami-Dade – Certificates of Use | D25: https://gis-mdc.opendata.arcgis.com/datasets/1952228619b0463cb6f9f7dc839bff88
A26: Broward GeoHub – Business Tax Records | D26: https://geohub-bcgis.opendata.arcgis.com/datasets/business-tax-records/about
A27: Sunbiz – descargas masivas (SFTP) | D27: https://dos.fl.gov/sunbiz/other-services/data-downloads/
A28: DBPR – búsqueda de licencias | D28: https://www2.myfloridalicense.com/

Sheet Metodologia
A1: Metodología, alcance y limitaciones
A2: Investigación de escritorio con fuentes públicas gratuitas. Fecha de corte: septiembre 2026.
A4: Tema | B4: Detalle
A5: Objetivo | B5: Identificar empresas medianas/establecidas en Miami-Dade y Broward (Fort Lauderdale, Kendall, Miami Beach, Medley, Doral, Hialeah, Homestead y alrededores) sin sitio web, con sitio obsoleto o con presencia digital fragmentada.
A6: Fuentes | B6: Census (QuickFacts, CBP, ABS, BFS), Florida Division of Corporations (Sunbiz), DBPR, tax collectors de Miami-Dade y Broward, sitios municipales, FDACS, FTC, Florida Senate; directorios públicos (BBB, Manta, Yelp, YellowPages, D&B, Bizapedia); benchmarks WordStream/LocaliQ.
A7: Criterio estado web | B7: Sin sitio web = ningún dominio propio en resultados de búsqueda. Sitio obsoleto = señales técnicas (http sin HTTPS, .html estático, plantilla sin personalizar, erratas). Presencia desordenada = varios dominios/fichas duplicadas. Tiene web (auditar) = dominio propio, calidad no auditada.
A8: Limitación 1 | B8: El estado web se infirió de fragmentos de búsqueda, no de visitas a cada sitio. Verificar antes de contactar.
A9: Limitación 2 | B9: Forma legal inferida del sufijo del nombre (Inc/LLC/Corp) salvo que se indique Sunbiz. Columna 'Estado Sunbiz' queda 'Pendiente' para validación manual en search.sunbiz.org.
A10: Limitación 3 | B10: Empleados y ventas = estimaciones de Manta/D&B. Establecimientos 20–499 empleados por condado = estimado con proporciones nacionales.
A11: Limitación 4 | B11: Muestra: 95 empresas (no censo). Sesgo hacia industrias con presencia en directorios. Cobertura baja en Miami Beach, Wynwood, restaurantes y salud.
A12: Siguiente fase | B12: Descargar datasets BTR (Miami-Dade, Broward) + archivo trimestral Sunbiz → cruzar por dirección → verificar dominio automáticamente (DNS/HTTP) → escalar a miles de prospectos con estado web medido.
A13: Cumplimiento | B13: Contacto recomendado: email B2B 1 a 1 conforme a CAN-SPAM y visita presencial. Evitar marcadores automáticos y SMS masivos (FTSA/TCPA).
